package y9;

import a9.f;
import f9.l;
import java.util.Set;
import l9.w;
import l9.y;
import p8.i0;

public final class a
  implements y
{
  private final b a;
  private volatile Set<String> b;
  private volatile a c;
  
  public a(b paramb)
  {
    this.a = paramb;
    this.b = i0.b();
    this.c = a.a;
  }
  
  private final boolean b(w paramw)
  {
    paramw = paramw.a("Content-Encoding");
    boolean bool2 = false;
    if (paramw == null) {
      return false;
    }
    boolean bool1 = bool2;
    if (!l.l(paramw, "identity", true))
    {
      bool1 = bool2;
      if (!l.l(paramw, "gzip", true)) {
        bool1 = true;
      }
    }
    return bool1;
  }
  
  private final void d(w paramw, int paramInt)
  {
    String str;
    if (this.b.contains(paramw.c(paramInt))) {
      str = "██";
    } else {
      str = paramw.f(paramInt);
    }
    b localb = this.a;
    StringBuilder localStringBuilder = new StringBuilder();
    localStringBuilder.append(paramw.c(paramInt));
    localStringBuilder.append(": ");
    localStringBuilder.append(str);
    localb.b(localStringBuilder.toString());
  }
  
  /* Error */
  public l9.f0 a(l9.y.a parama)
  {
    // Byte code:
    //   0: aload_1
    //   1: ldc 98
    //   3: invokestatic 27	a9/f:f	(Ljava/lang/Object;Ljava/lang/String;)V
    //   6: aload_0
    //   7: getfield 43	y9/a:c	Ly9/a$a;
    //   10: astore 10
    //   12: aload_1
    //   13: invokeinterface 104 1 0
    //   18: astore 13
    //   20: aload 10
    //   22: getstatic 41	y9/a$a:a	Ly9/a$a;
    //   25: if_acmpne +12 -> 37
    //   28: aload_1
    //   29: aload 13
    //   31: invokeinterface 107 2 0
    //   36: areturn
    //   37: aload 10
    //   39: getstatic 109	y9/a$a:d	Ly9/a$a;
    //   42: if_acmpne +8 -> 50
    //   45: iconst_1
    //   46: istore_3
    //   47: goto +5 -> 52
    //   50: iconst_0
    //   51: istore_3
    //   52: iload_3
    //   53: ifne +19 -> 72
    //   56: aload 10
    //   58: getstatic 110	y9/a$a:c	Ly9/a$a;
    //   61: if_acmpne +6 -> 67
    //   64: goto +8 -> 72
    //   67: iconst_0
    //   68: istore_2
    //   69: goto +5 -> 74
    //   72: iconst_1
    //   73: istore_2
    //   74: aload 13
    //   76: invokevirtual 115	l9/d0:a	()Ll9/e0;
    //   79: astore 12
    //   81: aload_1
    //   82: invokeinterface 118 1 0
    //   87: astore 10
    //   89: new 79	java/lang/StringBuilder
    //   92: dup
    //   93: invokespecial 80	java/lang/StringBuilder:<init>	()V
    //   96: astore 11
    //   98: aload 11
    //   100: ldc 120
    //   102: invokevirtual 84	java/lang/StringBuilder:append	(Ljava/lang/String;)Ljava/lang/StringBuilder;
    //   105: pop
    //   106: aload 11
    //   108: aload 13
    //   110: invokevirtual 123	l9/d0:g	()Ljava/lang/String;
    //   113: invokevirtual 84	java/lang/StringBuilder:append	(Ljava/lang/String;)Ljava/lang/StringBuilder;
    //   116: pop
    //   117: aload 11
    //   119: bipush 32
    //   121: invokevirtual 126	java/lang/StringBuilder:append	(C)Ljava/lang/StringBuilder;
    //   124: pop
    //   125: aload 11
    //   127: aload 13
    //   129: invokevirtual 130	l9/d0:j	()Ll9/x;
    //   132: invokevirtual 133	java/lang/StringBuilder:append	(Ljava/lang/Object;)Ljava/lang/StringBuilder;
    //   135: pop
    //   136: aload 10
    //   138: ifnull +20 -> 158
    //   141: ldc 135
    //   143: aload 10
    //   145: invokeinterface 140 1 0
    //   150: invokestatic 144	a9/f:m	(Ljava/lang/String;Ljava/lang/Object;)Ljava/lang/String;
    //   153: astore 10
    //   155: goto +7 -> 162
    //   158: ldc 146
    //   160: astore 10
    //   162: aload 11
    //   164: aload 10
    //   166: invokevirtual 84	java/lang/StringBuilder:append	(Ljava/lang/String;)Ljava/lang/StringBuilder;
    //   169: pop
    //   170: aload 11
    //   172: invokevirtual 90	java/lang/StringBuilder:toString	()Ljava/lang/String;
    //   175: astore 11
    //   177: aload 11
    //   179: astore 10
    //   181: iload_2
    //   182: ifne +63 -> 245
    //   185: aload 11
    //   187: astore 10
    //   189: aload 12
    //   191: ifnull +54 -> 245
    //   194: new 79	java/lang/StringBuilder
    //   197: dup
    //   198: invokespecial 80	java/lang/StringBuilder:<init>	()V
    //   201: astore 10
    //   203: aload 10
    //   205: aload 11
    //   207: invokevirtual 84	java/lang/StringBuilder:append	(Ljava/lang/String;)Ljava/lang/StringBuilder;
    //   210: pop
    //   211: aload 10
    //   213: ldc 148
    //   215: invokevirtual 84	java/lang/StringBuilder:append	(Ljava/lang/String;)Ljava/lang/StringBuilder;
    //   218: pop
    //   219: aload 10
    //   221: aload 12
    //   223: invokevirtual 153	l9/e0:a	()J
    //   226: invokevirtual 156	java/lang/StringBuilder:append	(J)Ljava/lang/StringBuilder;
    //   229: pop
    //   230: aload 10
    //   232: ldc 158
    //   234: invokevirtual 84	java/lang/StringBuilder:append	(Ljava/lang/String;)Ljava/lang/StringBuilder;
    //   237: pop
    //   238: aload 10
    //   240: invokevirtual 90	java/lang/StringBuilder:toString	()Ljava/lang/String;
    //   243: astore 10
    //   245: aload_0
    //   246: getfield 32	y9/a:a	Ly9/a$b;
    //   249: aload 10
    //   251: invokeinterface 93 2 0
    //   256: iload_2
    //   257: ifeq +738 -> 995
    //   260: aload 13
    //   262: invokevirtual 162	l9/d0:e	()Ll9/w;
    //   265: astore 11
    //   267: aload 12
    //   269: ifnull +91 -> 360
    //   272: aload 12
    //   274: invokevirtual 165	l9/e0:b	()Ll9/z;
    //   277: astore 10
    //   279: aload 10
    //   281: ifnonnull +6 -> 287
    //   284: goto +29 -> 313
    //   287: aload 11
    //   289: ldc 167
    //   291: invokevirtual 52	l9/w:a	(Ljava/lang/String;)Ljava/lang/String;
    //   294: ifnonnull +19 -> 313
    //   297: aload_0
    //   298: getfield 32	y9/a:a	Ly9/a$b;
    //   301: ldc 169
    //   303: aload 10
    //   305: invokestatic 144	a9/f:m	(Ljava/lang/String;Ljava/lang/Object;)Ljava/lang/String;
    //   308: invokeinterface 93 2 0
    //   313: aload 12
    //   315: invokevirtual 153	l9/e0:a	()J
    //   318: ldc2_w 170
    //   321: lcmp
    //   322: ifeq +38 -> 360
    //   325: aload 11
    //   327: ldc 173
    //   329: invokevirtual 52	l9/w:a	(Ljava/lang/String;)Ljava/lang/String;
    //   332: ifnonnull +28 -> 360
    //   335: aload_0
    //   336: getfield 32	y9/a:a	Ly9/a$b;
    //   339: ldc 175
    //   341: aload 12
    //   343: invokevirtual 153	l9/e0:a	()J
    //   346: invokestatic 181	java/lang/Long:valueOf	(J)Ljava/lang/Long;
    //   349: invokestatic 144	a9/f:m	(Ljava/lang/String;Ljava/lang/Object;)Ljava/lang/String;
    //   352: invokeinterface 93 2 0
    //   357: goto +3 -> 360
    //   360: aload 11
    //   362: invokevirtual 185	l9/w:size	()I
    //   365: istore 5
    //   367: iconst_0
    //   368: istore 4
    //   370: iload 4
    //   372: iload 5
    //   374: if_icmpge +20 -> 394
    //   377: aload_0
    //   378: aload 11
    //   380: iload 4
    //   382: invokespecial 187	y9/a:d	(Ll9/w;I)V
    //   385: iload 4
    //   387: iconst_1
    //   388: iadd
    //   389: istore 4
    //   391: goto -21 -> 370
    //   394: iload_3
    //   395: ifeq +570 -> 965
    //   398: aload 12
    //   400: ifnonnull +6 -> 406
    //   403: goto +562 -> 965
    //   406: aload_0
    //   407: aload 13
    //   409: invokevirtual 162	l9/d0:e	()Ll9/w;
    //   412: invokespecial 189	y9/a:b	(Ll9/w;)Z
    //   415: ifeq +64 -> 479
    //   418: aload_0
    //   419: getfield 32	y9/a:a	Ly9/a$b;
    //   422: astore 11
    //   424: new 79	java/lang/StringBuilder
    //   427: dup
    //   428: invokespecial 80	java/lang/StringBuilder:<init>	()V
    //   431: astore 12
    //   433: aload 12
    //   435: ldc 191
    //   437: invokevirtual 84	java/lang/StringBuilder:append	(Ljava/lang/String;)Ljava/lang/StringBuilder;
    //   440: pop
    //   441: aload 12
    //   443: aload 13
    //   445: invokevirtual 123	l9/d0:g	()Ljava/lang/String;
    //   448: invokevirtual 84	java/lang/StringBuilder:append	(Ljava/lang/String;)Ljava/lang/StringBuilder;
    //   451: pop
    //   452: ldc 193
    //   454: astore 10
    //   456: aload 12
    //   458: aload 10
    //   460: invokevirtual 84	java/lang/StringBuilder:append	(Ljava/lang/String;)Ljava/lang/StringBuilder;
    //   463: pop
    //   464: aload 11
    //   466: aload 12
    //   468: invokevirtual 90	java/lang/StringBuilder:toString	()Ljava/lang/String;
    //   471: invokeinterface 93 2 0
    //   476: goto +519 -> 995
    //   479: aload 12
    //   481: invokevirtual 196	l9/e0:e	()Z
    //   484: ifeq +44 -> 528
    //   487: aload_0
    //   488: getfield 32	y9/a:a	Ly9/a$b;
    //   491: astore 11
    //   493: new 79	java/lang/StringBuilder
    //   496: dup
    //   497: invokespecial 80	java/lang/StringBuilder:<init>	()V
    //   500: astore 12
    //   502: aload 12
    //   504: ldc 191
    //   506: invokevirtual 84	java/lang/StringBuilder:append	(Ljava/lang/String;)Ljava/lang/StringBuilder;
    //   509: pop
    //   510: aload 12
    //   512: aload 13
    //   514: invokevirtual 123	l9/d0:g	()Ljava/lang/String;
    //   517: invokevirtual 84	java/lang/StringBuilder:append	(Ljava/lang/String;)Ljava/lang/StringBuilder;
    //   520: pop
    //   521: ldc 198
    //   523: astore 10
    //   525: goto -69 -> 456
    //   528: aload 12
    //   530: invokevirtual 200	l9/e0:f	()Z
    //   533: ifeq +44 -> 577
    //   536: aload_0
    //   537: getfield 32	y9/a:a	Ly9/a$b;
    //   540: astore 11
    //   542: new 79	java/lang/StringBuilder
    //   545: dup
    //   546: invokespecial 80	java/lang/StringBuilder:<init>	()V
    //   549: astore 12
    //   551: aload 12
    //   553: ldc 191
    //   555: invokevirtual 84	java/lang/StringBuilder:append	(Ljava/lang/String;)Ljava/lang/StringBuilder;
    //   558: pop
    //   559: aload 12
    //   561: aload 13
    //   563: invokevirtual 123	l9/d0:g	()Ljava/lang/String;
    //   566: invokevirtual 84	java/lang/StringBuilder:append	(Ljava/lang/String;)Ljava/lang/StringBuilder;
    //   569: pop
    //   570: ldc 202
    //   572: astore 10
    //   574: goto -118 -> 456
    //   577: new 204	aa/b
    //   580: dup
    //   581: invokespecial 205	aa/b:<init>	()V
    //   584: astore 10
    //   586: aload 12
    //   588: aload 10
    //   590: invokevirtual 208	l9/e0:g	(Laa/c;)V
    //   593: ldc 62
    //   595: aload 11
    //   597: ldc 47
    //   599: invokevirtual 52	l9/w:a	(Ljava/lang/String;)Ljava/lang/String;
    //   602: iconst_1
    //   603: invokestatic 60	f9/l:l	(Ljava/lang/String;Ljava/lang/String;Z)Z
    //   606: ifeq +64 -> 670
    //   609: aload 10
    //   611: invokevirtual 211	aa/b:z0	()J
    //   614: invokestatic 181	java/lang/Long:valueOf	(J)Ljava/lang/Long;
    //   617: astore 11
    //   619: new 213	aa/i
    //   622: dup
    //   623: aload 10
    //   625: invokespecial 216	aa/i:<init>	(Laa/x;)V
    //   628: astore 14
    //   630: new 204	aa/b
    //   633: dup
    //   634: invokespecial 205	aa/b:<init>	()V
    //   637: astore 10
    //   639: aload 10
    //   641: aload 14
    //   643: invokevirtual 220	aa/b:G0	(Laa/x;)J
    //   646: pop2
    //   647: aload 14
    //   649: aconst_null
    //   650: invokestatic 225	y8/a:a	(Ljava/io/Closeable;Ljava/lang/Throwable;)V
    //   653: goto +20 -> 673
    //   656: astore_1
    //   657: aload_1
    //   658: athrow
    //   659: astore 10
    //   661: aload 14
    //   663: aload_1
    //   664: invokestatic 225	y8/a:a	(Ljava/io/Closeable;Ljava/lang/Throwable;)V
    //   667: aload 10
    //   669: athrow
    //   670: aconst_null
    //   671: astore 11
    //   673: aload 12
    //   675: invokevirtual 165	l9/e0:b	()Ll9/z;
    //   678: aconst_null
    //   679: iconst_1
    //   680: aconst_null
    //   681: invokestatic 230	m9/a:b	(Ll9/z;Ljava/nio/charset/Charset;ILjava/lang/Object;)Ljava/nio/charset/Charset;
    //   684: astore 14
    //   686: aload_0
    //   687: getfield 32	y9/a:a	Ly9/a$b;
    //   690: ldc 146
    //   692: invokeinterface 93 2 0
    //   697: aload 10
    //   699: invokestatic 235	z9/a:a	(Laa/b;)Z
    //   702: ifne +79 -> 781
    //   705: aload_0
    //   706: getfield 32	y9/a:a	Ly9/a$b;
    //   709: astore 10
    //   711: new 79	java/lang/StringBuilder
    //   714: dup
    //   715: invokespecial 80	java/lang/StringBuilder:<init>	()V
    //   718: astore 11
    //   720: aload 11
    //   722: ldc 191
    //   724: invokevirtual 84	java/lang/StringBuilder:append	(Ljava/lang/String;)Ljava/lang/StringBuilder;
    //   727: pop
    //   728: aload 11
    //   730: aload 13
    //   732: invokevirtual 123	l9/d0:g	()Ljava/lang/String;
    //   735: invokevirtual 84	java/lang/StringBuilder:append	(Ljava/lang/String;)Ljava/lang/StringBuilder;
    //   738: pop
    //   739: aload 11
    //   741: ldc 237
    //   743: invokevirtual 84	java/lang/StringBuilder:append	(Ljava/lang/String;)Ljava/lang/StringBuilder;
    //   746: pop
    //   747: aload 11
    //   749: aload 12
    //   751: invokevirtual 153	l9/e0:a	()J
    //   754: invokevirtual 156	java/lang/StringBuilder:append	(J)Ljava/lang/StringBuilder;
    //   757: pop
    //   758: aload 11
    //   760: ldc 239
    //   762: invokevirtual 84	java/lang/StringBuilder:append	(Ljava/lang/String;)Ljava/lang/StringBuilder;
    //   765: pop
    //   766: aload 10
    //   768: aload 11
    //   770: invokevirtual 90	java/lang/StringBuilder:toString	()Ljava/lang/String;
    //   773: invokeinterface 93 2 0
    //   778: goto +217 -> 995
    //   781: aload 11
    //   783: ifnull +95 -> 878
    //   786: aload_0
    //   787: getfield 32	y9/a:a	Ly9/a$b;
    //   790: astore 12
    //   792: new 79	java/lang/StringBuilder
    //   795: dup
    //   796: invokespecial 80	java/lang/StringBuilder:<init>	()V
    //   799: astore 14
    //   801: aload 14
    //   803: ldc 191
    //   805: invokevirtual 84	java/lang/StringBuilder:append	(Ljava/lang/String;)Ljava/lang/StringBuilder;
    //   808: pop
    //   809: aload 14
    //   811: aload 13
    //   813: invokevirtual 123	l9/d0:g	()Ljava/lang/String;
    //   816: invokevirtual 84	java/lang/StringBuilder:append	(Ljava/lang/String;)Ljava/lang/StringBuilder;
    //   819: pop
    //   820: aload 14
    //   822: ldc 148
    //   824: invokevirtual 84	java/lang/StringBuilder:append	(Ljava/lang/String;)Ljava/lang/StringBuilder;
    //   827: pop
    //   828: aload 14
    //   830: aload 10
    //   832: invokevirtual 211	aa/b:z0	()J
    //   835: invokevirtual 156	java/lang/StringBuilder:append	(J)Ljava/lang/StringBuilder;
    //   838: pop
    //   839: aload 14
    //   841: ldc 241
    //   843: invokevirtual 84	java/lang/StringBuilder:append	(Ljava/lang/String;)Ljava/lang/StringBuilder;
    //   846: pop
    //   847: aload 14
    //   849: aload 11
    //   851: invokevirtual 133	java/lang/StringBuilder:append	(Ljava/lang/Object;)Ljava/lang/StringBuilder;
    //   854: pop
    //   855: aload 14
    //   857: ldc 243
    //   859: invokevirtual 84	java/lang/StringBuilder:append	(Ljava/lang/String;)Ljava/lang/StringBuilder;
    //   862: pop
    //   863: aload 12
    //   865: aload 14
    //   867: invokevirtual 90	java/lang/StringBuilder:toString	()Ljava/lang/String;
    //   870: invokeinterface 93 2 0
    //   875: goto +120 -> 995
    //   878: aload_0
    //   879: getfield 32	y9/a:a	Ly9/a$b;
    //   882: aload 10
    //   884: aload 14
    //   886: invokevirtual 247	aa/b:u0	(Ljava/nio/charset/Charset;)Ljava/lang/String;
    //   889: invokeinterface 93 2 0
    //   894: aload_0
    //   895: getfield 32	y9/a:a	Ly9/a$b;
    //   898: astore 11
    //   900: new 79	java/lang/StringBuilder
    //   903: dup
    //   904: invokespecial 80	java/lang/StringBuilder:<init>	()V
    //   907: astore 10
    //   909: aload 10
    //   911: ldc 191
    //   913: invokevirtual 84	java/lang/StringBuilder:append	(Ljava/lang/String;)Ljava/lang/StringBuilder;
    //   916: pop
    //   917: aload 10
    //   919: aload 13
    //   921: invokevirtual 123	l9/d0:g	()Ljava/lang/String;
    //   924: invokevirtual 84	java/lang/StringBuilder:append	(Ljava/lang/String;)Ljava/lang/StringBuilder;
    //   927: pop
    //   928: aload 10
    //   930: ldc 148
    //   932: invokevirtual 84	java/lang/StringBuilder:append	(Ljava/lang/String;)Ljava/lang/StringBuilder;
    //   935: pop
    //   936: aload 10
    //   938: aload 12
    //   940: invokevirtual 153	l9/e0:a	()J
    //   943: invokevirtual 156	java/lang/StringBuilder:append	(J)Ljava/lang/StringBuilder;
    //   946: pop
    //   947: aload 10
    //   949: ldc 158
    //   951: invokevirtual 84	java/lang/StringBuilder:append	(Ljava/lang/String;)Ljava/lang/StringBuilder;
    //   954: pop
    //   955: aload 10
    //   957: invokevirtual 90	java/lang/StringBuilder:toString	()Ljava/lang/String;
    //   960: astore 10
    //   962: goto +21 -> 983
    //   965: aload_0
    //   966: getfield 32	y9/a:a	Ly9/a$b;
    //   969: astore 11
    //   971: ldc 191
    //   973: aload 13
    //   975: invokevirtual 123	l9/d0:g	()Ljava/lang/String;
    //   978: invokestatic 144	a9/f:m	(Ljava/lang/String;Ljava/lang/Object;)Ljava/lang/String;
    //   981: astore 10
    //   983: aload 11
    //   985: aload 10
    //   987: invokeinterface 93 2 0
    //   992: goto +3 -> 995
    //   995: iload_2
    //   996: istore 4
    //   998: invokestatic 252	java/lang/System:nanoTime	()J
    //   1001: lstore 6
    //   1003: aload_1
    //   1004: aload 13
    //   1006: invokeinterface 107 2 0
    //   1011: astore 12
    //   1013: getstatic 258	java/util/concurrent/TimeUnit:NANOSECONDS	Ljava/util/concurrent/TimeUnit;
    //   1016: invokestatic 252	java/lang/System:nanoTime	()J
    //   1019: lload 6
    //   1021: lsub
    //   1022: invokevirtual 262	java/util/concurrent/TimeUnit:toMillis	(J)J
    //   1025: lstore 6
    //   1027: aload 12
    //   1029: invokevirtual 267	l9/f0:a	()Ll9/g0;
    //   1032: astore 11
    //   1034: aload 11
    //   1036: invokestatic 270	a9/f:c	(Ljava/lang/Object;)V
    //   1039: aload 11
    //   1041: invokevirtual 275	l9/g0:i	()J
    //   1044: lstore 8
    //   1046: lload 8
    //   1048: ldc2_w 170
    //   1051: lcmp
    //   1052: ifeq +34 -> 1086
    //   1055: new 79	java/lang/StringBuilder
    //   1058: dup
    //   1059: invokespecial 80	java/lang/StringBuilder:<init>	()V
    //   1062: astore_1
    //   1063: aload_1
    //   1064: lload 8
    //   1066: invokevirtual 156	java/lang/StringBuilder:append	(J)Ljava/lang/StringBuilder;
    //   1069: pop
    //   1070: aload_1
    //   1071: ldc_w 277
    //   1074: invokevirtual 84	java/lang/StringBuilder:append	(Ljava/lang/String;)Ljava/lang/StringBuilder;
    //   1077: pop
    //   1078: aload_1
    //   1079: invokevirtual 90	java/lang/StringBuilder:toString	()Ljava/lang/String;
    //   1082: astore_1
    //   1083: goto +7 -> 1090
    //   1086: ldc_w 279
    //   1089: astore_1
    //   1090: aload_0
    //   1091: getfield 32	y9/a:a	Ly9/a$b;
    //   1094: astore 13
    //   1096: new 79	java/lang/StringBuilder
    //   1099: dup
    //   1100: invokespecial 80	java/lang/StringBuilder:<init>	()V
    //   1103: astore 14
    //   1105: aload 14
    //   1107: ldc_w 281
    //   1110: invokevirtual 84	java/lang/StringBuilder:append	(Ljava/lang/String;)Ljava/lang/StringBuilder;
    //   1113: pop
    //   1114: aload 14
    //   1116: aload 12
    //   1118: invokevirtual 284	l9/f0:B	()I
    //   1121: invokevirtual 287	java/lang/StringBuilder:append	(I)Ljava/lang/StringBuilder;
    //   1124: pop
    //   1125: aload 12
    //   1127: invokevirtual 290	l9/f0:k0	()Ljava/lang/String;
    //   1130: invokeinterface 295 1 0
    //   1135: ifne +8 -> 1143
    //   1138: iconst_1
    //   1139: istore_2
    //   1140: goto +5 -> 1145
    //   1143: iconst_0
    //   1144: istore_2
    //   1145: iload_2
    //   1146: ifeq +10 -> 1156
    //   1149: ldc 146
    //   1151: astore 10
    //   1153: goto +42 -> 1195
    //   1156: aload 12
    //   1158: invokevirtual 290	l9/f0:k0	()Ljava/lang/String;
    //   1161: astore 10
    //   1163: new 79	java/lang/StringBuilder
    //   1166: dup
    //   1167: invokespecial 80	java/lang/StringBuilder:<init>	()V
    //   1170: astore 15
    //   1172: aload 15
    //   1174: bipush 32
    //   1176: invokevirtual 126	java/lang/StringBuilder:append	(C)Ljava/lang/StringBuilder;
    //   1179: pop
    //   1180: aload 15
    //   1182: aload 10
    //   1184: invokevirtual 84	java/lang/StringBuilder:append	(Ljava/lang/String;)Ljava/lang/StringBuilder;
    //   1187: pop
    //   1188: aload 15
    //   1190: invokevirtual 90	java/lang/StringBuilder:toString	()Ljava/lang/String;
    //   1193: astore 10
    //   1195: aload 14
    //   1197: aload 10
    //   1199: invokevirtual 84	java/lang/StringBuilder:append	(Ljava/lang/String;)Ljava/lang/StringBuilder;
    //   1202: pop
    //   1203: aload 14
    //   1205: bipush 32
    //   1207: invokevirtual 126	java/lang/StringBuilder:append	(C)Ljava/lang/StringBuilder;
    //   1210: pop
    //   1211: aload 14
    //   1213: aload 12
    //   1215: invokevirtual 298	l9/f0:q0	()Ll9/d0;
    //   1218: invokevirtual 130	l9/d0:j	()Ll9/x;
    //   1221: invokevirtual 133	java/lang/StringBuilder:append	(Ljava/lang/Object;)Ljava/lang/StringBuilder;
    //   1224: pop
    //   1225: aload 14
    //   1227: ldc 148
    //   1229: invokevirtual 84	java/lang/StringBuilder:append	(Ljava/lang/String;)Ljava/lang/StringBuilder;
    //   1232: pop
    //   1233: aload 14
    //   1235: lload 6
    //   1237: invokevirtual 156	java/lang/StringBuilder:append	(J)Ljava/lang/StringBuilder;
    //   1240: pop
    //   1241: aload 14
    //   1243: ldc_w 300
    //   1246: invokevirtual 84	java/lang/StringBuilder:append	(Ljava/lang/String;)Ljava/lang/StringBuilder;
    //   1249: pop
    //   1250: iload 4
    //   1252: ifne +46 -> 1298
    //   1255: new 79	java/lang/StringBuilder
    //   1258: dup
    //   1259: invokespecial 80	java/lang/StringBuilder:<init>	()V
    //   1262: astore 10
    //   1264: aload 10
    //   1266: ldc_w 302
    //   1269: invokevirtual 84	java/lang/StringBuilder:append	(Ljava/lang/String;)Ljava/lang/StringBuilder;
    //   1272: pop
    //   1273: aload 10
    //   1275: aload_1
    //   1276: invokevirtual 84	java/lang/StringBuilder:append	(Ljava/lang/String;)Ljava/lang/StringBuilder;
    //   1279: pop
    //   1280: aload 10
    //   1282: ldc_w 304
    //   1285: invokevirtual 84	java/lang/StringBuilder:append	(Ljava/lang/String;)Ljava/lang/StringBuilder;
    //   1288: pop
    //   1289: aload 10
    //   1291: invokevirtual 90	java/lang/StringBuilder:toString	()Ljava/lang/String;
    //   1294: astore_1
    //   1295: goto +6 -> 1301
    //   1298: ldc 146
    //   1300: astore_1
    //   1301: aload 14
    //   1303: aload_1
    //   1304: invokevirtual 84	java/lang/StringBuilder:append	(Ljava/lang/String;)Ljava/lang/StringBuilder;
    //   1307: pop
    //   1308: aload 14
    //   1310: bipush 41
    //   1312: invokevirtual 126	java/lang/StringBuilder:append	(C)Ljava/lang/StringBuilder;
    //   1315: pop
    //   1316: aload 13
    //   1318: aload 14
    //   1320: invokevirtual 90	java/lang/StringBuilder:toString	()Ljava/lang/String;
    //   1323: invokeinterface 93 2 0
    //   1328: iload 4
    //   1330: ifeq +460 -> 1790
    //   1333: aload 12
    //   1335: invokevirtual 307	l9/f0:i0	()Ll9/w;
    //   1338: astore 10
    //   1340: aload 10
    //   1342: invokevirtual 185	l9/w:size	()I
    //   1345: istore 4
    //   1347: iconst_0
    //   1348: istore_2
    //   1349: iload_2
    //   1350: iload 4
    //   1352: if_icmpge +17 -> 1369
    //   1355: aload_0
    //   1356: aload 10
    //   1358: iload_2
    //   1359: invokespecial 187	y9/a:d	(Ll9/w;I)V
    //   1362: iload_2
    //   1363: iconst_1
    //   1364: iadd
    //   1365: istore_2
    //   1366: goto -17 -> 1349
    //   1369: iload_3
    //   1370: ifeq +402 -> 1772
    //   1373: aload 12
    //   1375: invokestatic 312	r9/e:b	(Ll9/f0;)Z
    //   1378: ifne +6 -> 1384
    //   1381: goto +391 -> 1772
    //   1384: aload_0
    //   1385: aload 12
    //   1387: invokevirtual 307	l9/f0:i0	()Ll9/w;
    //   1390: invokespecial 189	y9/a:b	(Ll9/w;)Z
    //   1393: ifeq +16 -> 1409
    //   1396: aload_0
    //   1397: getfield 32	y9/a:a	Ly9/a$b;
    //   1400: astore_1
    //   1401: ldc_w 314
    //   1404: astore 10
    //   1406: goto +376 -> 1782
    //   1409: aload 11
    //   1411: invokevirtual 318	l9/g0:e0	()Laa/d;
    //   1414: astore_1
    //   1415: aload_1
    //   1416: ldc2_w 319
    //   1419: invokeinterface 326 3 0
    //   1424: pop
    //   1425: aload_1
    //   1426: invokeinterface 329 1 0
    //   1431: astore_1
    //   1432: ldc 62
    //   1434: aload 10
    //   1436: ldc 47
    //   1438: invokevirtual 52	l9/w:a	(Ljava/lang/String;)Ljava/lang/String;
    //   1441: iconst_1
    //   1442: invokestatic 60	f9/l:l	(Ljava/lang/String;Ljava/lang/String;Z)Z
    //   1445: ifeq +63 -> 1508
    //   1448: aload_1
    //   1449: invokevirtual 211	aa/b:z0	()J
    //   1452: invokestatic 181	java/lang/Long:valueOf	(J)Ljava/lang/Long;
    //   1455: astore 10
    //   1457: new 213	aa/i
    //   1460: dup
    //   1461: aload_1
    //   1462: invokevirtual 331	aa/b:e0	()Laa/b;
    //   1465: invokespecial 216	aa/i:<init>	(Laa/x;)V
    //   1468: astore 13
    //   1470: new 204	aa/b
    //   1473: dup
    //   1474: invokespecial 205	aa/b:<init>	()V
    //   1477: astore_1
    //   1478: aload_1
    //   1479: aload 13
    //   1481: invokevirtual 220	aa/b:G0	(Laa/x;)J
    //   1484: pop2
    //   1485: aload 13
    //   1487: aconst_null
    //   1488: invokestatic 225	y8/a:a	(Ljava/io/Closeable;Ljava/lang/Throwable;)V
    //   1491: goto +20 -> 1511
    //   1494: astore_1
    //   1495: aload_1
    //   1496: athrow
    //   1497: astore 10
    //   1499: aload 13
    //   1501: aload_1
    //   1502: invokestatic 225	y8/a:a	(Ljava/io/Closeable;Ljava/lang/Throwable;)V
    //   1505: aload 10
    //   1507: athrow
    //   1508: aconst_null
    //   1509: astore 10
    //   1511: aload 11
    //   1513: invokevirtual 333	l9/g0:B	()Ll9/z;
    //   1516: aconst_null
    //   1517: iconst_1
    //   1518: aconst_null
    //   1519: invokestatic 230	m9/a:b	(Ll9/z;Ljava/nio/charset/Charset;ILjava/lang/Object;)Ljava/nio/charset/Charset;
    //   1522: astore 11
    //   1524: aload_1
    //   1525: invokestatic 235	z9/a:a	(Laa/b;)Z
    //   1528: ifne +71 -> 1599
    //   1531: aload_0
    //   1532: getfield 32	y9/a:a	Ly9/a$b;
    //   1535: ldc 146
    //   1537: invokeinterface 93 2 0
    //   1542: aload_0
    //   1543: getfield 32	y9/a:a	Ly9/a$b;
    //   1546: astore 10
    //   1548: new 79	java/lang/StringBuilder
    //   1551: dup
    //   1552: invokespecial 80	java/lang/StringBuilder:<init>	()V
    //   1555: astore 11
    //   1557: aload 11
    //   1559: ldc_w 335
    //   1562: invokevirtual 84	java/lang/StringBuilder:append	(Ljava/lang/String;)Ljava/lang/StringBuilder;
    //   1565: pop
    //   1566: aload 11
    //   1568: aload_1
    //   1569: invokevirtual 211	aa/b:z0	()J
    //   1572: invokevirtual 156	java/lang/StringBuilder:append	(J)Ljava/lang/StringBuilder;
    //   1575: pop
    //   1576: aload 11
    //   1578: ldc 239
    //   1580: invokevirtual 84	java/lang/StringBuilder:append	(Ljava/lang/String;)Ljava/lang/StringBuilder;
    //   1583: pop
    //   1584: aload 10
    //   1586: aload 11
    //   1588: invokevirtual 90	java/lang/StringBuilder:toString	()Ljava/lang/String;
    //   1591: invokeinterface 93 2 0
    //   1596: aload 12
    //   1598: areturn
    //   1599: lload 8
    //   1601: lconst_0
    //   1602: lcmp
    //   1603: ifeq +32 -> 1635
    //   1606: aload_0
    //   1607: getfield 32	y9/a:a	Ly9/a$b;
    //   1610: ldc 146
    //   1612: invokeinterface 93 2 0
    //   1617: aload_0
    //   1618: getfield 32	y9/a:a	Ly9/a$b;
    //   1621: aload_1
    //   1622: invokevirtual 331	aa/b:e0	()Laa/b;
    //   1625: aload 11
    //   1627: invokevirtual 247	aa/b:u0	(Ljava/nio/charset/Charset;)Ljava/lang/String;
    //   1630: invokeinterface 93 2 0
    //   1635: aload 10
    //   1637: ifnull +76 -> 1713
    //   1640: aload_0
    //   1641: getfield 32	y9/a:a	Ly9/a$b;
    //   1644: astore 11
    //   1646: new 79	java/lang/StringBuilder
    //   1649: dup
    //   1650: invokespecial 80	java/lang/StringBuilder:<init>	()V
    //   1653: astore 13
    //   1655: aload 13
    //   1657: ldc_w 337
    //   1660: invokevirtual 84	java/lang/StringBuilder:append	(Ljava/lang/String;)Ljava/lang/StringBuilder;
    //   1663: pop
    //   1664: aload 13
    //   1666: aload_1
    //   1667: invokevirtual 211	aa/b:z0	()J
    //   1670: invokevirtual 156	java/lang/StringBuilder:append	(J)Ljava/lang/StringBuilder;
    //   1673: pop
    //   1674: aload 13
    //   1676: ldc 241
    //   1678: invokevirtual 84	java/lang/StringBuilder:append	(Ljava/lang/String;)Ljava/lang/StringBuilder;
    //   1681: pop
    //   1682: aload 13
    //   1684: aload 10
    //   1686: invokevirtual 133	java/lang/StringBuilder:append	(Ljava/lang/Object;)Ljava/lang/StringBuilder;
    //   1689: pop
    //   1690: aload 13
    //   1692: ldc 243
    //   1694: invokevirtual 84	java/lang/StringBuilder:append	(Ljava/lang/String;)Ljava/lang/StringBuilder;
    //   1697: pop
    //   1698: aload 11
    //   1700: aload 13
    //   1702: invokevirtual 90	java/lang/StringBuilder:toString	()Ljava/lang/String;
    //   1705: invokeinterface 93 2 0
    //   1710: aload 12
    //   1712: areturn
    //   1713: aload_0
    //   1714: getfield 32	y9/a:a	Ly9/a$b;
    //   1717: astore 10
    //   1719: new 79	java/lang/StringBuilder
    //   1722: dup
    //   1723: invokespecial 80	java/lang/StringBuilder:<init>	()V
    //   1726: astore 11
    //   1728: aload 11
    //   1730: ldc_w 337
    //   1733: invokevirtual 84	java/lang/StringBuilder:append	(Ljava/lang/String;)Ljava/lang/StringBuilder;
    //   1736: pop
    //   1737: aload 11
    //   1739: aload_1
    //   1740: invokevirtual 211	aa/b:z0	()J
    //   1743: invokevirtual 156	java/lang/StringBuilder:append	(J)Ljava/lang/StringBuilder;
    //   1746: pop
    //   1747: aload 11
    //   1749: ldc 158
    //   1751: invokevirtual 84	java/lang/StringBuilder:append	(Ljava/lang/String;)Ljava/lang/StringBuilder;
    //   1754: pop
    //   1755: aload 11
    //   1757: invokevirtual 90	java/lang/StringBuilder:toString	()Ljava/lang/String;
    //   1760: astore 11
    //   1762: aload 10
    //   1764: astore_1
    //   1765: aload 11
    //   1767: astore 10
    //   1769: goto +13 -> 1782
    //   1772: aload_0
    //   1773: getfield 32	y9/a:a	Ly9/a$b;
    //   1776: astore_1
    //   1777: ldc_w 339
    //   1780: astore 10
    //   1782: aload_1
    //   1783: aload 10
    //   1785: invokeinterface 93 2 0
    //   1790: aload 12
    //   1792: areturn
    //   1793: astore_1
    //   1794: aload_0
    //   1795: getfield 32	y9/a:a	Ly9/a$b;
    //   1798: ldc_w 341
    //   1801: aload_1
    //   1802: invokestatic 144	a9/f:m	(Ljava/lang/String;Ljava/lang/Object;)Ljava/lang/String;
    //   1805: invokeinterface 93 2 0
    //   1810: aload_1
    //   1811: athrow
    // Local variable table:
    //   start	length	slot	name	signature
    //   0	1812	0	this	a
    //   0	1812	1	parama	l9.y.a
    //   68	1298	2	i	int
    //   46	1324	3	j	int
    //   368	985	4	k	int
    //   365	10	5	m	int
    //   1001	235	6	l1	long
    //   1044	556	8	l2	long
    //   10	630	10	localObject1	Object
    //   659	39	10	localb	aa.b
    //   709	747	10	localObject2	Object
    //   1497	9	10	localObject3	Object
    //   1509	275	10	localObject4	Object
    //   96	1670	11	localObject5	Object
    //   79	1712	12	localObject6	Object
    //   18	1683	13	localObject7	Object
    //   628	691	14	localObject8	Object
    //   1170	19	15	localStringBuilder	StringBuilder
    // Exception table:
    //   from	to	target	type
    //   630	647	656	finally
    //   657	659	659	finally
    //   1470	1485	1494	finally
    //   1495	1497	1497	finally
    //   1003	1013	1793	java/lang/Exception
  }
  
  public final void c(a parama)
  {
    f.f(parama, "<set-?>");
    this.c = parama;
  }
  
  public final a e(a parama)
  {
    f.f(parama, "level");
    c(parama);
    return this;
  }
  
  public static enum a
  {
    private a() {}
  }
  
  public static abstract interface b
  {
    public abstract void b(String paramString);
  }
}


/* Location:           E:\android_tools\AndroidKiller_v1.3.1\projects\hoxin-release\ProjectSrc\smali\
 * Qualified Name:     y9.a
 * JD-Core Version:    0.7.0.1
 */