package com.baidu.location.e;

import java.net.URL;
import java.util.Map;
import java.util.concurrent.ExecutorService;
import javax.net.ssl.HostnameVerifier;
import javax.net.ssl.SSLSession;

public abstract class f
{
  private static String a = "10.0.0.172";
  private static int b = 80;
  public static int f = a.f;
  protected static int o;
  public String g = null;
  public int h = 1;
  public String i = null;
  public Map<String, Object> j = null;
  public String k = null;
  public byte[] l = null;
  public byte[] m = null;
  public String n = null;
  
  public abstract void a();
  
  public void a(ExecutorService paramExecutorService, final String paramString)
  {
    try
    {
      paramExecutorService.execute(new Runnable()
      {
        /* Error */
        public void run()
        {
          // Byte code:
          //   0: aload_0
          //   1: getfield 18	com/baidu/location/e/f$3:b	Lcom/baidu/location/e/f;
          //   4: invokevirtual 31	com/baidu/location/e/f:a	()V
          //   7: aload_0
          //   8: getfield 18	com/baidu/location/e/f$3:b	Lcom/baidu/location/e/f;
          //   11: aload_0
          //   12: getfield 20	com/baidu/location/e/f$3:a	Ljava/lang/String;
          //   15: putfield 34	com/baidu/location/e/f:g	Ljava/lang/String;
          //   18: aconst_null
          //   19: astore 5
          //   21: aconst_null
          //   22: astore_2
          //   23: new 36	java/lang/StringBuffer
          //   26: dup
          //   27: invokespecial 37	java/lang/StringBuffer:<init>	()V
          //   30: astore 4
          //   32: new 39	java/net/URL
          //   35: dup
          //   36: aload_0
          //   37: getfield 18	com/baidu/location/e/f$3:b	Lcom/baidu/location/e/f;
          //   40: getfield 34	com/baidu/location/e/f:g	Ljava/lang/String;
          //   43: invokespecial 42	java/net/URL:<init>	(Ljava/lang/String;)V
          //   46: invokevirtual 46	java/net/URL:openConnection	()Ljava/net/URLConnection;
          //   49: checkcast 48	javax/net/ssl/HttpsURLConnection
          //   52: astore_3
          //   53: aload_3
          //   54: iconst_0
          //   55: invokevirtual 52	javax/net/ssl/HttpsURLConnection:setInstanceFollowRedirects	(Z)V
          //   58: aload_3
          //   59: iconst_1
          //   60: invokevirtual 55	javax/net/ssl/HttpsURLConnection:setDoOutput	(Z)V
          //   63: aload_3
          //   64: iconst_1
          //   65: invokevirtual 58	javax/net/ssl/HttpsURLConnection:setDoInput	(Z)V
          //   68: aload_3
          //   69: getstatic 63	com/baidu/location/e/a:a	I
          //   72: invokevirtual 67	javax/net/ssl/HttpsURLConnection:setConnectTimeout	(I)V
          //   75: aload_3
          //   76: getstatic 69	com/baidu/location/e/a:b	I
          //   79: invokevirtual 72	javax/net/ssl/HttpsURLConnection:setReadTimeout	(I)V
          //   82: aload_3
          //   83: ldc 74
          //   85: invokevirtual 77	javax/net/ssl/HttpsURLConnection:setRequestMethod	(Ljava/lang/String;)V
          //   88: aload_3
          //   89: ldc 79
          //   91: ldc 81
          //   93: invokevirtual 85	javax/net/ssl/HttpsURLConnection:setRequestProperty	(Ljava/lang/String;Ljava/lang/String;)V
          //   96: aload_3
          //   97: ldc 87
          //   99: ldc 89
          //   101: invokevirtual 85	javax/net/ssl/HttpsURLConnection:setRequestProperty	(Ljava/lang/String;Ljava/lang/String;)V
          //   104: getstatic 94	com/baidu/location/e/h:aw	Ljava/lang/String;
          //   107: astore 5
          //   109: aload 5
          //   111: ifnull +11 -> 122
          //   114: aload_3
          //   115: ldc 96
          //   117: aload 5
          //   119: invokevirtual 85	javax/net/ssl/HttpsURLConnection:setRequestProperty	(Ljava/lang/String;Ljava/lang/String;)V
          //   122: aload_0
          //   123: getfield 18	com/baidu/location/e/f$3:b	Lcom/baidu/location/e/f;
          //   126: getfield 100	com/baidu/location/e/f:j	Ljava/util/Map;
          //   129: invokeinterface 106 1 0
          //   134: invokeinterface 112 1 0
          //   139: astore 5
          //   141: aload 5
          //   143: invokeinterface 118 1 0
          //   148: ifeq +63 -> 211
          //   151: aload 5
          //   153: invokeinterface 122 1 0
          //   158: checkcast 124	java/util/Map$Entry
          //   161: astore 6
          //   163: aload 4
          //   165: aload 6
          //   167: invokeinterface 127 1 0
          //   172: checkcast 129	java/lang/String
          //   175: invokevirtual 133	java/lang/StringBuffer:append	(Ljava/lang/String;)Ljava/lang/StringBuffer;
          //   178: pop
          //   179: aload 4
          //   181: ldc 135
          //   183: invokevirtual 133	java/lang/StringBuffer:append	(Ljava/lang/String;)Ljava/lang/StringBuffer;
          //   186: pop
          //   187: aload 4
          //   189: aload 6
          //   191: invokeinterface 138 1 0
          //   196: invokevirtual 141	java/lang/StringBuffer:append	(Ljava/lang/Object;)Ljava/lang/StringBuffer;
          //   199: pop
          //   200: aload 4
          //   202: ldc 143
          //   204: invokevirtual 133	java/lang/StringBuffer:append	(Ljava/lang/String;)Ljava/lang/StringBuffer;
          //   207: pop
          //   208: goto -67 -> 141
          //   211: aload 4
          //   213: invokevirtual 147	java/lang/StringBuffer:length	()I
          //   216: ifle +16 -> 232
          //   219: aload 4
          //   221: aload 4
          //   223: invokevirtual 147	java/lang/StringBuffer:length	()I
          //   226: iconst_1
          //   227: isub
          //   228: invokevirtual 151	java/lang/StringBuffer:deleteCharAt	(I)Ljava/lang/StringBuffer;
          //   231: pop
          //   232: aload_3
          //   233: invokevirtual 155	javax/net/ssl/HttpsURLConnection:getOutputStream	()Ljava/io/OutputStream;
          //   236: astore 5
          //   238: aload 5
          //   240: aload 4
          //   242: invokevirtual 159	java/lang/StringBuffer:toString	()Ljava/lang/String;
          //   245: invokevirtual 163	java/lang/String:getBytes	()[B
          //   248: invokevirtual 169	java/io/OutputStream:write	([B)V
          //   251: aload 5
          //   253: invokevirtual 172	java/io/OutputStream:flush	()V
          //   256: aload_3
          //   257: invokevirtual 175	javax/net/ssl/HttpsURLConnection:getResponseCode	()I
          //   260: sipush 200
          //   263: if_icmpne +301 -> 564
          //   266: aload_3
          //   267: invokevirtual 179	javax/net/ssl/HttpsURLConnection:getInputStream	()Ljava/io/InputStream;
          //   270: astore 4
          //   272: aload 4
          //   274: astore 6
          //   276: aload 4
          //   278: astore 8
          //   280: aload 4
          //   282: astore 9
          //   284: aload_3
          //   285: invokevirtual 182	javax/net/ssl/HttpsURLConnection:getContentEncoding	()Ljava/lang/String;
          //   288: astore 7
          //   290: aload 4
          //   292: astore_2
          //   293: aload 7
          //   295: ifnull +57 -> 352
          //   298: aload 4
          //   300: astore_2
          //   301: aload 4
          //   303: astore 6
          //   305: aload 4
          //   307: astore 8
          //   309: aload 4
          //   311: astore 9
          //   313: aload 7
          //   315: ldc 89
          //   317: invokevirtual 186	java/lang/String:contains	(Ljava/lang/CharSequence;)Z
          //   320: ifeq +32 -> 352
          //   323: aload 4
          //   325: astore 6
          //   327: aload 4
          //   329: astore 8
          //   331: aload 4
          //   333: astore 9
          //   335: new 188	java/util/zip/GZIPInputStream
          //   338: dup
          //   339: new 190	java/io/BufferedInputStream
          //   342: dup
          //   343: aload 4
          //   345: invokespecial 193	java/io/BufferedInputStream:<init>	(Ljava/io/InputStream;)V
          //   348: invokespecial 194	java/util/zip/GZIPInputStream:<init>	(Ljava/io/InputStream;)V
          //   351: astore_2
          //   352: aload_2
          //   353: astore 6
          //   355: aload_2
          //   356: astore 8
          //   358: aload_2
          //   359: astore 9
          //   361: new 196	java/io/ByteArrayOutputStream
          //   364: dup
          //   365: invokespecial 197	java/io/ByteArrayOutputStream:<init>	()V
          //   368: astore 7
          //   370: aload_2
          //   371: astore 6
          //   373: aload_3
          //   374: astore 8
          //   376: aload 5
          //   378: astore 9
          //   380: aload 7
          //   382: astore 10
          //   384: sipush 1024
          //   387: newarray byte
          //   389: astore 4
          //   391: aload_2
          //   392: astore 6
          //   394: aload_3
          //   395: astore 8
          //   397: aload 5
          //   399: astore 9
          //   401: aload 7
          //   403: astore 10
          //   405: aload_2
          //   406: aload 4
          //   408: invokevirtual 203	java/io/InputStream:read	([B)I
          //   411: istore_1
          //   412: iload_1
          //   413: iconst_m1
          //   414: if_icmpeq +29 -> 443
          //   417: aload_2
          //   418: astore 6
          //   420: aload_3
          //   421: astore 8
          //   423: aload 5
          //   425: astore 9
          //   427: aload 7
          //   429: astore 10
          //   431: aload 7
          //   433: aload 4
          //   435: iconst_0
          //   436: iload_1
          //   437: invokevirtual 206	java/io/ByteArrayOutputStream:write	([BII)V
          //   440: goto -49 -> 391
          //   443: aload_2
          //   444: astore 6
          //   446: aload_3
          //   447: astore 8
          //   449: aload 5
          //   451: astore 9
          //   453: aload 7
          //   455: astore 10
          //   457: aload_0
          //   458: getfield 18	com/baidu/location/e/f$3:b	Lcom/baidu/location/e/f;
          //   461: new 129	java/lang/String
          //   464: dup
          //   465: aload 7
          //   467: invokevirtual 209	java/io/ByteArrayOutputStream:toByteArray	()[B
          //   470: ldc 211
          //   472: invokespecial 214	java/lang/String:<init>	([BLjava/lang/String;)V
          //   475: putfield 217	com/baidu/location/e/f:i	Ljava/lang/String;
          //   478: aload_2
          //   479: astore 6
          //   481: aload_3
          //   482: astore 8
          //   484: aload 5
          //   486: astore 9
          //   488: aload 7
          //   490: astore 10
          //   492: aload_0
          //   493: getfield 18	com/baidu/location/e/f$3:b	Lcom/baidu/location/e/f;
          //   496: iconst_1
          //   497: invokevirtual 219	com/baidu/location/e/f:a	(Z)V
          //   500: goto +85 -> 585
          //   503: astore 11
          //   505: aload_2
          //   506: astore 4
          //   508: aload 7
          //   510: astore_2
          //   511: goto +222 -> 733
          //   514: astore 11
          //   516: aload_2
          //   517: astore 4
          //   519: aload 7
          //   521: astore_2
          //   522: goto +383 -> 905
          //   525: astore_2
          //   526: aconst_null
          //   527: astore 7
          //   529: aload 6
          //   531: astore 4
          //   533: aload_3
          //   534: astore 8
          //   536: aload 7
          //   538: astore_3
          //   539: goto +545 -> 1084
          //   542: astore 11
          //   544: aconst_null
          //   545: astore_2
          //   546: aload 8
          //   548: astore 4
          //   550: goto +183 -> 733
          //   553: astore 11
          //   555: aconst_null
          //   556: astore_2
          //   557: aload 9
          //   559: astore 4
          //   561: goto +344 -> 905
          //   564: aload_0
          //   565: getfield 18	com/baidu/location/e/f$3:b	Lcom/baidu/location/e/f;
          //   568: astore 4
          //   570: aload 4
          //   572: aconst_null
          //   573: putfield 217	com/baidu/location/e/f:i	Ljava/lang/String;
          //   576: aload 4
          //   578: iconst_0
          //   579: invokevirtual 219	com/baidu/location/e/f:a	(Z)V
          //   582: aconst_null
          //   583: astore 7
          //   585: aload_3
          //   586: invokevirtual 222	javax/net/ssl/HttpsURLConnection:disconnect	()V
          //   589: aload 5
          //   591: invokevirtual 225	java/io/OutputStream:close	()V
          //   594: goto +11 -> 605
          //   597: ldc 227
          //   599: ldc 229
          //   601: invokestatic 235	android/util/Log:d	(Ljava/lang/String;Ljava/lang/String;)I
          //   604: pop
          //   605: aload_2
          //   606: ifnull +18 -> 624
          //   609: aload_2
          //   610: invokevirtual 236	java/io/InputStream:close	()V
          //   613: goto +11 -> 624
          //   616: ldc 227
          //   618: ldc 238
          //   620: invokestatic 235	android/util/Log:d	(Ljava/lang/String;Ljava/lang/String;)I
          //   623: pop
          //   624: aload 7
          //   626: ifnull +445 -> 1071
          //   629: aload 7
          //   631: astore_2
          //   632: goto +428 -> 1060
          //   635: astore_2
          //   636: aconst_null
          //   637: astore 4
          //   639: aload 4
          //   641: astore 6
          //   643: aload_3
          //   644: astore 8
          //   646: aload 6
          //   648: astore_3
          //   649: goto +435 -> 1084
          //   652: astore 11
          //   654: aconst_null
          //   655: astore 4
          //   657: aload 4
          //   659: astore_2
          //   660: goto +73 -> 733
          //   663: astore 11
          //   665: aconst_null
          //   666: astore 4
          //   668: aload 4
          //   670: astore_2
          //   671: goto +234 -> 905
          //   674: astore_2
          //   675: aconst_null
          //   676: astore 4
          //   678: aload 4
          //   680: astore 5
          //   682: aload 5
          //   684: astore 6
          //   686: aload_3
          //   687: astore 8
          //   689: aload 6
          //   691: astore_3
          //   692: goto +392 -> 1084
          //   695: astore 11
          //   697: goto +28 -> 725
          //   700: astore 11
          //   702: goto +195 -> 897
          //   705: astore_3
          //   706: aconst_null
          //   707: astore 4
          //   709: aload 4
          //   711: astore_2
          //   712: aload_2
          //   713: astore 6
          //   715: aload_2
          //   716: astore 7
          //   718: goto +379 -> 1097
          //   721: astore 11
          //   723: aconst_null
          //   724: astore_3
          //   725: aconst_null
          //   726: astore 5
          //   728: aconst_null
          //   729: astore 4
          //   731: aconst_null
          //   732: astore_2
          //   733: aload 4
          //   735: astore 6
          //   737: aload_3
          //   738: astore 8
          //   740: aload 5
          //   742: astore 9
          //   744: aload_2
          //   745: astore 10
          //   747: aload 11
          //   749: invokevirtual 241	java/lang/Error:printStackTrace	()V
          //   752: aload 4
          //   754: astore 6
          //   756: aload_3
          //   757: astore 8
          //   759: aload 5
          //   761: astore 9
          //   763: aload_2
          //   764: astore 10
          //   766: ldc 227
          //   768: ldc 243
          //   770: invokestatic 245	android/util/Log:i	(Ljava/lang/String;Ljava/lang/String;)I
          //   773: pop
          //   774: aload 4
          //   776: astore 6
          //   778: aload_3
          //   779: astore 8
          //   781: aload 5
          //   783: astore 9
          //   785: aload_2
          //   786: astore 10
          //   788: aload_0
          //   789: getfield 18	com/baidu/location/e/f$3:b	Lcom/baidu/location/e/f;
          //   792: astore 7
          //   794: aload 4
          //   796: astore 6
          //   798: aload_3
          //   799: astore 8
          //   801: aload 5
          //   803: astore 9
          //   805: aload_2
          //   806: astore 10
          //   808: aload 7
          //   810: aconst_null
          //   811: putfield 217	com/baidu/location/e/f:i	Ljava/lang/String;
          //   814: aload 4
          //   816: astore 6
          //   818: aload_3
          //   819: astore 8
          //   821: aload 5
          //   823: astore 9
          //   825: aload_2
          //   826: astore 10
          //   828: aload 7
          //   830: iconst_0
          //   831: invokevirtual 219	com/baidu/location/e/f:a	(Z)V
          //   834: aload_3
          //   835: ifnull +7 -> 842
          //   838: aload_3
          //   839: invokevirtual 222	javax/net/ssl/HttpsURLConnection:disconnect	()V
          //   842: aload 5
          //   844: ifnull +19 -> 863
          //   847: aload 5
          //   849: invokevirtual 225	java/io/OutputStream:close	()V
          //   852: goto +11 -> 863
          //   855: ldc 227
          //   857: ldc 229
          //   859: invokestatic 235	android/util/Log:d	(Ljava/lang/String;Ljava/lang/String;)I
          //   862: pop
          //   863: aload 4
          //   865: ifnull +19 -> 884
          //   868: aload 4
          //   870: invokevirtual 236	java/io/InputStream:close	()V
          //   873: goto +11 -> 884
          //   876: ldc 227
          //   878: ldc 238
          //   880: invokestatic 235	android/util/Log:d	(Ljava/lang/String;Ljava/lang/String;)I
          //   883: pop
          //   884: aload_2
          //   885: ifnull +186 -> 1071
          //   888: aload_2
          //   889: invokevirtual 246	java/io/ByteArrayOutputStream:close	()V
          //   892: return
          //   893: astore 11
          //   895: aconst_null
          //   896: astore_3
          //   897: aconst_null
          //   898: astore 5
          //   900: aconst_null
          //   901: astore 4
          //   903: aconst_null
          //   904: astore_2
          //   905: aload 4
          //   907: astore 6
          //   909: aload_3
          //   910: astore 8
          //   912: aload 5
          //   914: astore 9
          //   916: aload_2
          //   917: astore 10
          //   919: aload 11
          //   921: invokevirtual 247	java/lang/Exception:printStackTrace	()V
          //   924: aload 4
          //   926: astore 6
          //   928: aload_3
          //   929: astore 8
          //   931: aload 5
          //   933: astore 9
          //   935: aload_2
          //   936: astore 10
          //   938: ldc 227
          //   940: ldc 249
          //   942: invokestatic 245	android/util/Log:i	(Ljava/lang/String;Ljava/lang/String;)I
          //   945: pop
          //   946: aload 4
          //   948: astore 6
          //   950: aload_3
          //   951: astore 8
          //   953: aload 5
          //   955: astore 9
          //   957: aload_2
          //   958: astore 10
          //   960: aload_0
          //   961: getfield 18	com/baidu/location/e/f$3:b	Lcom/baidu/location/e/f;
          //   964: astore 7
          //   966: aload 4
          //   968: astore 6
          //   970: aload_3
          //   971: astore 8
          //   973: aload 5
          //   975: astore 9
          //   977: aload_2
          //   978: astore 10
          //   980: aload 7
          //   982: aconst_null
          //   983: putfield 217	com/baidu/location/e/f:i	Ljava/lang/String;
          //   986: aload 4
          //   988: astore 6
          //   990: aload_3
          //   991: astore 8
          //   993: aload 5
          //   995: astore 9
          //   997: aload_2
          //   998: astore 10
          //   1000: aload 7
          //   1002: iconst_0
          //   1003: invokevirtual 219	com/baidu/location/e/f:a	(Z)V
          //   1006: aload_3
          //   1007: ifnull +7 -> 1014
          //   1010: aload_3
          //   1011: invokevirtual 222	javax/net/ssl/HttpsURLConnection:disconnect	()V
          //   1014: aload 5
          //   1016: ifnull +19 -> 1035
          //   1019: aload 5
          //   1021: invokevirtual 225	java/io/OutputStream:close	()V
          //   1024: goto +11 -> 1035
          //   1027: ldc 227
          //   1029: ldc 229
          //   1031: invokestatic 235	android/util/Log:d	(Ljava/lang/String;Ljava/lang/String;)I
          //   1034: pop
          //   1035: aload 4
          //   1037: ifnull +19 -> 1056
          //   1040: aload 4
          //   1042: invokevirtual 236	java/io/InputStream:close	()V
          //   1045: goto +11 -> 1056
          //   1048: ldc 227
          //   1050: ldc 238
          //   1052: invokestatic 235	android/util/Log:d	(Ljava/lang/String;Ljava/lang/String;)I
          //   1055: pop
          //   1056: aload_2
          //   1057: ifnull +14 -> 1071
          //   1060: goto -172 -> 888
          //   1063: ldc 227
          //   1065: ldc 251
          //   1067: invokestatic 235	android/util/Log:d	(Ljava/lang/String;Ljava/lang/String;)I
          //   1070: pop
          //   1071: return
          //   1072: astore_2
          //   1073: aload 10
          //   1075: astore_3
          //   1076: aload 9
          //   1078: astore 5
          //   1080: aload 6
          //   1082: astore 4
          //   1084: aload_3
          //   1085: astore 6
          //   1087: aload 5
          //   1089: astore 7
          //   1091: aload 8
          //   1093: astore 5
          //   1095: aload_2
          //   1096: astore_3
          //   1097: aload 5
          //   1099: ifnull +8 -> 1107
          //   1102: aload 5
          //   1104: invokevirtual 222	javax/net/ssl/HttpsURLConnection:disconnect	()V
          //   1107: aload 7
          //   1109: ifnull +19 -> 1128
          //   1112: aload 7
          //   1114: invokevirtual 225	java/io/OutputStream:close	()V
          //   1117: goto +11 -> 1128
          //   1120: ldc 227
          //   1122: ldc 229
          //   1124: invokestatic 235	android/util/Log:d	(Ljava/lang/String;Ljava/lang/String;)I
          //   1127: pop
          //   1128: aload 4
          //   1130: ifnull +19 -> 1149
          //   1133: aload 4
          //   1135: invokevirtual 236	java/io/InputStream:close	()V
          //   1138: goto +11 -> 1149
          //   1141: ldc 227
          //   1143: ldc 238
          //   1145: invokestatic 235	android/util/Log:d	(Ljava/lang/String;Ljava/lang/String;)I
          //   1148: pop
          //   1149: aload 6
          //   1151: ifnull +19 -> 1170
          //   1154: aload 6
          //   1156: invokevirtual 246	java/io/ByteArrayOutputStream:close	()V
          //   1159: goto +11 -> 1170
          //   1162: ldc 227
          //   1164: ldc 251
          //   1166: invokestatic 235	android/util/Log:d	(Ljava/lang/String;Ljava/lang/String;)I
          //   1169: pop
          //   1170: aload_3
          //   1171: athrow
          //   1172: astore_3
          //   1173: goto -576 -> 597
          //   1176: astore_2
          //   1177: goto -561 -> 616
          //   1180: astore_3
          //   1181: goto -326 -> 855
          //   1184: astore_3
          //   1185: goto -309 -> 876
          //   1188: astore_2
          //   1189: goto -126 -> 1063
          //   1192: astore_3
          //   1193: goto -166 -> 1027
          //   1196: astore_3
          //   1197: goto -149 -> 1048
          //   1200: astore_2
          //   1201: goto -81 -> 1120
          //   1204: astore_2
          //   1205: goto -64 -> 1141
          //   1208: astore_2
          //   1209: goto -47 -> 1162
          // Local variable table:
          //   start	length	slot	name	signature
          //   0	1212	0	this	3
          //   411	26	1	i	int
          //   22	500	2	localObject1	Object
          //   525	1	2	localObject2	Object
          //   545	87	2	localObject3	Object
          //   635	1	2	localObject4	Object
          //   659	12	2	localObject5	Object
          //   674	1	2	localObject6	Object
          //   711	346	2	localObject7	Object
          //   1072	24	2	localObject8	Object
          //   1176	1	2	localException1	java.lang.Exception
          //   1188	1	2	localException2	java.lang.Exception
          //   1200	1	2	localException3	java.lang.Exception
          //   1204	1	2	localException4	java.lang.Exception
          //   1208	1	2	localException5	java.lang.Exception
          //   52	640	3	localObject9	Object
          //   705	1	3	localObject10	Object
          //   724	447	3	localObject11	Object
          //   1172	1	3	localException6	java.lang.Exception
          //   1180	1	3	localException7	java.lang.Exception
          //   1184	1	3	localException8	java.lang.Exception
          //   1192	1	3	localException9	java.lang.Exception
          //   1196	1	3	localException10	java.lang.Exception
          //   30	1104	4	localObject12	Object
          //   19	1084	5	localObject13	Object
          //   161	994	6	localObject14	Object
          //   288	825	7	localObject15	Object
          //   278	814	8	localObject16	Object
          //   282	795	9	localObject17	Object
          //   382	692	10	localObject18	Object
          //   503	1	11	localError1	java.lang.Error
          //   514	1	11	localException11	java.lang.Exception
          //   542	1	11	localError2	java.lang.Error
          //   553	1	11	localException12	java.lang.Exception
          //   652	1	11	localError3	java.lang.Error
          //   663	1	11	localException13	java.lang.Exception
          //   695	1	11	localError4	java.lang.Error
          //   700	1	11	localException14	java.lang.Exception
          //   721	27	11	localError5	java.lang.Error
          //   893	27	11	localException15	java.lang.Exception
          // Exception table:
          //   from	to	target	type
          //   384	391	503	java/lang/Error
          //   405	412	503	java/lang/Error
          //   431	440	503	java/lang/Error
          //   457	478	503	java/lang/Error
          //   492	500	503	java/lang/Error
          //   384	391	514	java/lang/Exception
          //   405	412	514	java/lang/Exception
          //   431	440	514	java/lang/Exception
          //   457	478	514	java/lang/Exception
          //   492	500	514	java/lang/Exception
          //   284	290	525	finally
          //   313	323	525	finally
          //   335	352	525	finally
          //   361	370	525	finally
          //   284	290	542	java/lang/Error
          //   313	323	542	java/lang/Error
          //   335	352	542	java/lang/Error
          //   361	370	542	java/lang/Error
          //   284	290	553	java/lang/Exception
          //   313	323	553	java/lang/Exception
          //   335	352	553	java/lang/Exception
          //   361	370	553	java/lang/Exception
          //   238	272	635	finally
          //   564	582	635	finally
          //   238	272	652	java/lang/Error
          //   564	582	652	java/lang/Error
          //   238	272	663	java/lang/Exception
          //   564	582	663	java/lang/Exception
          //   53	109	674	finally
          //   114	122	674	finally
          //   122	141	674	finally
          //   141	208	674	finally
          //   211	232	674	finally
          //   232	238	674	finally
          //   53	109	695	java/lang/Error
          //   114	122	695	java/lang/Error
          //   122	141	695	java/lang/Error
          //   141	208	695	java/lang/Error
          //   211	232	695	java/lang/Error
          //   232	238	695	java/lang/Error
          //   53	109	700	java/lang/Exception
          //   114	122	700	java/lang/Exception
          //   122	141	700	java/lang/Exception
          //   141	208	700	java/lang/Exception
          //   211	232	700	java/lang/Exception
          //   232	238	700	java/lang/Exception
          //   23	53	705	finally
          //   23	53	721	java/lang/Error
          //   23	53	893	java/lang/Exception
          //   384	391	1072	finally
          //   405	412	1072	finally
          //   431	440	1072	finally
          //   457	478	1072	finally
          //   492	500	1072	finally
          //   747	752	1072	finally
          //   766	774	1072	finally
          //   788	794	1072	finally
          //   808	814	1072	finally
          //   828	834	1072	finally
          //   919	924	1072	finally
          //   938	946	1072	finally
          //   960	966	1072	finally
          //   980	986	1072	finally
          //   1000	1006	1072	finally
          //   589	594	1172	java/lang/Exception
          //   609	613	1176	java/lang/Exception
          //   847	852	1180	java/lang/Exception
          //   868	873	1184	java/lang/Exception
          //   888	892	1188	java/lang/Exception
          //   1019	1024	1192	java/lang/Exception
          //   1040	1045	1196	java/lang/Exception
          //   1112	1117	1200	java/lang/Exception
          //   1133	1138	1204	java/lang/Exception
          //   1154	1159	1208	java/lang/Exception
        }
      });
      return;
    }
    finally
    {
      label16:
      break label16;
    }
    a(false);
  }
  
  public void a(ExecutorService paramExecutorService, final boolean paramBoolean, final String paramString)
  {
    try
    {
      paramExecutorService.execute(new Runnable()
      {
        /* Error */
        public void run()
        {
          // Byte code:
          //   0: aload_0
          //   1: getfield 20	com/baidu/location/e/f$1:c	Lcom/baidu/location/e/f;
          //   4: astore_3
          //   5: aload_3
          //   6: getstatic 37	com/baidu/location/e/d:c	Ljava/lang/String;
          //   9: putfield 40	com/baidu/location/e/f:g	Ljava/lang/String;
          //   12: aload_3
          //   13: invokevirtual 42	com/baidu/location/e/f:a	()V
          //   16: aload_0
          //   17: getfield 20	com/baidu/location/e/f$1:c	Lcom/baidu/location/e/f;
          //   20: getfield 46	com/baidu/location/e/f:h	I
          //   23: istore_2
          //   24: aconst_null
          //   25: astore 4
          //   27: iload_2
          //   28: ifle +1024 -> 1052
          //   31: new 48	java/net/URL
          //   34: dup
          //   35: aload_0
          //   36: getfield 20	com/baidu/location/e/f$1:c	Lcom/baidu/location/e/f;
          //   39: getfield 40	com/baidu/location/e/f:g	Ljava/lang/String;
          //   42: invokespecial 51	java/net/URL:<init>	(Ljava/lang/String;)V
          //   45: astore_3
          //   46: new 53	java/lang/StringBuffer
          //   49: dup
          //   50: invokespecial 54	java/lang/StringBuffer:<init>	()V
          //   53: astore 6
          //   55: aload_0
          //   56: getfield 20	com/baidu/location/e/f$1:c	Lcom/baidu/location/e/f;
          //   59: getfield 58	com/baidu/location/e/f:j	Ljava/util/Map;
          //   62: invokeinterface 64 1 0
          //   67: invokeinterface 70 1 0
          //   72: astore 5
          //   74: aload 5
          //   76: invokeinterface 76 1 0
          //   81: ifeq +63 -> 144
          //   84: aload 5
          //   86: invokeinterface 80 1 0
          //   91: checkcast 82	java/util/Map$Entry
          //   94: astore 7
          //   96: aload 6
          //   98: aload 7
          //   100: invokeinterface 85 1 0
          //   105: checkcast 87	java/lang/String
          //   108: invokevirtual 91	java/lang/StringBuffer:append	(Ljava/lang/String;)Ljava/lang/StringBuffer;
          //   111: pop
          //   112: aload 6
          //   114: ldc 93
          //   116: invokevirtual 91	java/lang/StringBuffer:append	(Ljava/lang/String;)Ljava/lang/StringBuffer;
          //   119: pop
          //   120: aload 6
          //   122: aload 7
          //   124: invokeinterface 96 1 0
          //   129: invokevirtual 99	java/lang/StringBuffer:append	(Ljava/lang/Object;)Ljava/lang/StringBuffer;
          //   132: pop
          //   133: aload 6
          //   135: ldc 101
          //   137: invokevirtual 91	java/lang/StringBuffer:append	(Ljava/lang/String;)Ljava/lang/StringBuffer;
          //   140: pop
          //   141: goto -67 -> 74
          //   144: aload 6
          //   146: invokevirtual 105	java/lang/StringBuffer:length	()I
          //   149: ifle +16 -> 165
          //   152: aload 6
          //   154: aload 6
          //   156: invokevirtual 105	java/lang/StringBuffer:length	()I
          //   159: iconst_1
          //   160: isub
          //   161: invokevirtual 109	java/lang/StringBuffer:deleteCharAt	(I)Ljava/lang/StringBuffer;
          //   164: pop
          //   165: aload_3
          //   166: invokevirtual 113	java/net/URL:openConnection	()Ljava/net/URLConnection;
          //   169: checkcast 115	javax/net/ssl/HttpsURLConnection
          //   172: astore_3
          //   173: aload_3
          //   174: ldc 117
          //   176: invokevirtual 120	javax/net/ssl/HttpsURLConnection:setRequestMethod	(Ljava/lang/String;)V
          //   179: aload_3
          //   180: iconst_1
          //   181: invokevirtual 124	javax/net/ssl/HttpsURLConnection:setDoInput	(Z)V
          //   184: aload_3
          //   185: iconst_1
          //   186: invokevirtual 127	javax/net/ssl/HttpsURLConnection:setDoOutput	(Z)V
          //   189: aload_3
          //   190: iconst_0
          //   191: invokevirtual 130	javax/net/ssl/HttpsURLConnection:setUseCaches	(Z)V
          //   194: aload_3
          //   195: getstatic 134	com/baidu/location/e/a:a	I
          //   198: invokevirtual 138	javax/net/ssl/HttpsURLConnection:setConnectTimeout	(I)V
          //   201: aload_3
          //   202: getstatic 134	com/baidu/location/e/a:a	I
          //   205: invokevirtual 141	javax/net/ssl/HttpsURLConnection:setReadTimeout	(I)V
          //   208: aload_3
          //   209: ldc 143
          //   211: ldc 145
          //   213: invokevirtual 149	javax/net/ssl/HttpsURLConnection:setRequestProperty	(Ljava/lang/String;Ljava/lang/String;)V
          //   216: aload_3
          //   217: ldc 151
          //   219: ldc 153
          //   221: invokevirtual 149	javax/net/ssl/HttpsURLConnection:setRequestProperty	(Ljava/lang/String;Ljava/lang/String;)V
          //   224: aload_3
          //   225: ldc 155
          //   227: ldc 157
          //   229: invokevirtual 149	javax/net/ssl/HttpsURLConnection:setRequestProperty	(Ljava/lang/String;Ljava/lang/String;)V
          //   232: getstatic 162	com/baidu/location/e/h:aw	Ljava/lang/String;
          //   235: astore 4
          //   237: aload 4
          //   239: ifnull +11 -> 250
          //   242: aload_3
          //   243: ldc 164
          //   245: aload 4
          //   247: invokevirtual 149	javax/net/ssl/HttpsURLConnection:setRequestProperty	(Ljava/lang/String;Ljava/lang/String;)V
          //   250: aload_0
          //   251: getfield 22	com/baidu/location/e/f$1:a	Ljava/lang/String;
          //   254: invokestatic 170	android/text/TextUtils:isEmpty	(Ljava/lang/CharSequence;)Z
          //   257: ifne +13 -> 270
          //   260: aload_3
          //   261: ldc 172
          //   263: aload_0
          //   264: getfield 22	com/baidu/location/e/f$1:a	Ljava/lang/String;
          //   267: invokevirtual 149	javax/net/ssl/HttpsURLConnection:setRequestProperty	(Ljava/lang/String;Ljava/lang/String;)V
          //   270: aload_3
          //   271: invokevirtual 176	javax/net/ssl/HttpsURLConnection:getOutputStream	()Ljava/io/OutputStream;
          //   274: astore 5
          //   276: aload 5
          //   278: aload 6
          //   280: invokevirtual 180	java/lang/StringBuffer:toString	()Ljava/lang/String;
          //   283: invokevirtual 184	java/lang/String:getBytes	()[B
          //   286: invokevirtual 190	java/io/OutputStream:write	([B)V
          //   289: aload 5
          //   291: invokevirtual 193	java/io/OutputStream:flush	()V
          //   294: aload_3
          //   295: invokevirtual 196	javax/net/ssl/HttpsURLConnection:getResponseCode	()I
          //   298: sipush 200
          //   301: if_icmpne +271 -> 572
          //   304: aload_3
          //   305: invokevirtual 200	javax/net/ssl/HttpsURLConnection:getInputStream	()Ljava/io/InputStream;
          //   308: astore 6
          //   310: aload 6
          //   312: astore 9
          //   314: aload 6
          //   316: astore 7
          //   318: aload 6
          //   320: astore 8
          //   322: aload_3
          //   323: invokevirtual 203	javax/net/ssl/HttpsURLConnection:getContentEncoding	()Ljava/lang/String;
          //   326: astore 10
          //   328: aload 6
          //   330: astore 4
          //   332: aload 10
          //   334: ifnull +59 -> 393
          //   337: aload 6
          //   339: astore 4
          //   341: aload 6
          //   343: astore 9
          //   345: aload 6
          //   347: astore 7
          //   349: aload 6
          //   351: astore 8
          //   353: aload 10
          //   355: ldc 157
          //   357: invokevirtual 206	java/lang/String:contains	(Ljava/lang/CharSequence;)Z
          //   360: ifeq +33 -> 393
          //   363: aload 6
          //   365: astore 9
          //   367: aload 6
          //   369: astore 7
          //   371: aload 6
          //   373: astore 8
          //   375: new 208	java/util/zip/GZIPInputStream
          //   378: dup
          //   379: new 210	java/io/BufferedInputStream
          //   382: dup
          //   383: aload 6
          //   385: invokespecial 213	java/io/BufferedInputStream:<init>	(Ljava/io/InputStream;)V
          //   388: invokespecial 214	java/util/zip/GZIPInputStream:<init>	(Ljava/io/InputStream;)V
          //   391: astore 4
          //   393: aload 4
          //   395: astore 9
          //   397: aload 4
          //   399: astore 7
          //   401: aload 4
          //   403: astore 8
          //   405: new 216	java/io/ByteArrayOutputStream
          //   408: dup
          //   409: invokespecial 217	java/io/ByteArrayOutputStream:<init>	()V
          //   412: astore 6
          //   414: sipush 1024
          //   417: newarray byte
          //   419: astore 7
          //   421: aload 4
          //   423: aload 7
          //   425: invokevirtual 223	java/io/InputStream:read	([B)I
          //   428: istore_1
          //   429: iload_1
          //   430: iconst_m1
          //   431: if_icmpeq +15 -> 446
          //   434: aload 6
          //   436: aload 7
          //   438: iconst_0
          //   439: iload_1
          //   440: invokevirtual 226	java/io/ByteArrayOutputStream:write	([BII)V
          //   443: goto -22 -> 421
          //   446: aload_0
          //   447: getfield 20	com/baidu/location/e/f$1:c	Lcom/baidu/location/e/f;
          //   450: new 87	java/lang/String
          //   453: dup
          //   454: aload 6
          //   456: invokevirtual 229	java/io/ByteArrayOutputStream:toByteArray	()[B
          //   459: ldc 231
          //   461: invokespecial 234	java/lang/String:<init>	([BLjava/lang/String;)V
          //   464: putfield 237	com/baidu/location/e/f:i	Ljava/lang/String;
          //   467: aload_0
          //   468: getfield 24	com/baidu/location/e/f$1:b	Z
          //   471: ifeq +15 -> 486
          //   474: aload_0
          //   475: getfield 20	com/baidu/location/e/f$1:c	Lcom/baidu/location/e/f;
          //   478: aload 6
          //   480: invokevirtual 229	java/io/ByteArrayOutputStream:toByteArray	()[B
          //   483: putfield 241	com/baidu/location/e/f:l	[B
          //   486: aload_0
          //   487: getfield 20	com/baidu/location/e/f$1:c	Lcom/baidu/location/e/f;
          //   490: iconst_1
          //   491: invokevirtual 243	com/baidu/location/e/f:a	(Z)V
          //   494: iconst_1
          //   495: istore_1
          //   496: goto +84 -> 580
          //   499: astore 8
          //   501: aload_3
          //   502: astore 7
          //   504: aload 8
          //   506: astore_3
          //   507: aload 4
          //   509: astore 8
          //   511: goto +460 -> 971
          //   514: aload 5
          //   516: astore 10
          //   518: aload 4
          //   520: astore 9
          //   522: goto +200 -> 722
          //   525: aload 5
          //   527: astore 10
          //   529: aload 4
          //   531: astore 9
          //   533: goto +299 -> 832
          //   536: astore 4
          //   538: aload_3
          //   539: astore 7
          //   541: aload 9
          //   543: astore 8
          //   545: aconst_null
          //   546: astore 6
          //   548: aload 4
          //   550: astore_3
          //   551: aload 6
          //   553: astore 4
          //   555: goto +420 -> 975
          //   558: aload 5
          //   560: astore 10
          //   562: goto +153 -> 715
          //   565: aload 5
          //   567: astore 10
          //   569: goto +256 -> 825
          //   572: iconst_0
          //   573: istore_1
          //   574: aconst_null
          //   575: astore 4
          //   577: aconst_null
          //   578: astore 6
          //   580: aload_3
          //   581: invokevirtual 246	javax/net/ssl/HttpsURLConnection:disconnect	()V
          //   584: aload 5
          //   586: invokevirtual 249	java/io/OutputStream:close	()V
          //   589: goto +11 -> 600
          //   592: ldc 251
          //   594: ldc 253
          //   596: invokestatic 259	android/util/Log:d	(Ljava/lang/String;Ljava/lang/String;)I
          //   599: pop
          //   600: aload 4
          //   602: ifnull +20 -> 622
          //   605: aload 4
          //   607: invokevirtual 260	java/io/InputStream:close	()V
          //   610: goto +12 -> 622
          //   613: ldc 251
          //   615: ldc_w 262
          //   618: invokestatic 259	android/util/Log:d	(Ljava/lang/String;Ljava/lang/String;)I
          //   621: pop
          //   622: aload 6
          //   624: ifnull +20 -> 644
          //   627: aload 6
          //   629: invokevirtual 263	java/io/ByteArrayOutputStream:close	()V
          //   632: goto +12 -> 644
          //   635: ldc 251
          //   637: ldc_w 265
          //   640: invokestatic 259	android/util/Log:d	(Ljava/lang/String;Ljava/lang/String;)I
          //   643: pop
          //   644: aload_3
          //   645: astore 4
          //   647: goto +293 -> 940
          //   650: astore 4
          //   652: aload_3
          //   653: astore 7
          //   655: aload 4
          //   657: astore_3
          //   658: goto +42 -> 700
          //   661: aload 5
          //   663: astore 10
          //   665: goto +47 -> 712
          //   668: aload 5
          //   670: astore 10
          //   672: goto +150 -> 822
          //   675: astore 5
          //   677: aload_3
          //   678: astore 4
          //   680: aload 5
          //   682: astore_3
          //   683: goto +10 -> 693
          //   686: goto +23 -> 709
          //   689: goto +130 -> 819
          //   692: astore_3
          //   693: aconst_null
          //   694: astore 5
          //   696: aload 4
          //   698: astore 7
          //   700: aconst_null
          //   701: astore 4
          //   703: aconst_null
          //   704: astore 8
          //   706: goto +269 -> 975
          //   709: aconst_null
          //   710: astore 10
          //   712: aconst_null
          //   713: astore 8
          //   715: aconst_null
          //   716: astore 6
          //   718: aload 8
          //   720: astore 9
          //   722: aload 10
          //   724: astore 4
          //   726: aload_3
          //   727: astore 5
          //   729: aload 9
          //   731: astore 7
          //   733: aload 6
          //   735: astore 8
          //   737: ldc 251
          //   739: ldc_w 267
          //   742: invokestatic 259	android/util/Log:d	(Ljava/lang/String;Ljava/lang/String;)I
          //   745: pop
          //   746: aload_3
          //   747: ifnull +7 -> 754
          //   750: aload_3
          //   751: invokevirtual 246	javax/net/ssl/HttpsURLConnection:disconnect	()V
          //   754: aload 10
          //   756: ifnull +19 -> 775
          //   759: aload 10
          //   761: invokevirtual 249	java/io/OutputStream:close	()V
          //   764: goto +11 -> 775
          //   767: ldc 251
          //   769: ldc 253
          //   771: invokestatic 259	android/util/Log:d	(Ljava/lang/String;Ljava/lang/String;)I
          //   774: pop
          //   775: aload 9
          //   777: ifnull +20 -> 797
          //   780: aload 9
          //   782: invokevirtual 260	java/io/InputStream:close	()V
          //   785: goto +12 -> 797
          //   788: ldc 251
          //   790: ldc_w 262
          //   793: invokestatic 259	android/util/Log:d	(Ljava/lang/String;Ljava/lang/String;)I
          //   796: pop
          //   797: aload_3
          //   798: astore 4
          //   800: aload 6
          //   802: ifnull +136 -> 938
          //   805: aload_3
          //   806: astore 4
          //   808: aload 6
          //   810: invokevirtual 263	java/io/ByteArrayOutputStream:close	()V
          //   813: aload_3
          //   814: astore 4
          //   816: goto +122 -> 938
          //   819: aconst_null
          //   820: astore 10
          //   822: aconst_null
          //   823: astore 7
          //   825: aconst_null
          //   826: astore 6
          //   828: aload 7
          //   830: astore 9
          //   832: aload 10
          //   834: astore 4
          //   836: aload_3
          //   837: astore 5
          //   839: aload 9
          //   841: astore 7
          //   843: aload 6
          //   845: astore 8
          //   847: ldc 251
          //   849: ldc_w 269
          //   852: invokestatic 259	android/util/Log:d	(Ljava/lang/String;Ljava/lang/String;)I
          //   855: pop
          //   856: aload_3
          //   857: ifnull +7 -> 864
          //   860: aload_3
          //   861: invokevirtual 246	javax/net/ssl/HttpsURLConnection:disconnect	()V
          //   864: aload 10
          //   866: ifnull +19 -> 885
          //   869: aload 10
          //   871: invokevirtual 249	java/io/OutputStream:close	()V
          //   874: goto +11 -> 885
          //   877: ldc 251
          //   879: ldc 253
          //   881: invokestatic 259	android/util/Log:d	(Ljava/lang/String;Ljava/lang/String;)I
          //   884: pop
          //   885: aload 9
          //   887: ifnull +20 -> 907
          //   890: aload 9
          //   892: invokevirtual 260	java/io/InputStream:close	()V
          //   895: goto +12 -> 907
          //   898: ldc 251
          //   900: ldc_w 262
          //   903: invokestatic 259	android/util/Log:d	(Ljava/lang/String;Ljava/lang/String;)I
          //   906: pop
          //   907: aload_3
          //   908: astore 4
          //   910: aload 6
          //   912: ifnull +26 -> 938
          //   915: aload_3
          //   916: astore 4
          //   918: aload 6
          //   920: invokevirtual 263	java/io/ByteArrayOutputStream:close	()V
          //   923: aload_3
          //   924: astore 4
          //   926: goto +12 -> 938
          //   929: ldc 251
          //   931: ldc_w 265
          //   934: invokestatic 259	android/util/Log:d	(Ljava/lang/String;Ljava/lang/String;)I
          //   937: pop
          //   938: iconst_0
          //   939: istore_1
          //   940: iload_1
          //   941: ifeq +6 -> 947
          //   944: goto +108 -> 1052
          //   947: iload_2
          //   948: iconst_1
          //   949: isub
          //   950: istore_2
          //   951: goto -924 -> 27
          //   954: astore_3
          //   955: aload 8
          //   957: astore 6
          //   959: aload 7
          //   961: astore 8
          //   963: aload 5
          //   965: astore 7
          //   967: aload 4
          //   969: astore 5
          //   971: aload 6
          //   973: astore 4
          //   975: aload 7
          //   977: ifnull +8 -> 985
          //   980: aload 7
          //   982: invokevirtual 246	javax/net/ssl/HttpsURLConnection:disconnect	()V
          //   985: aload 5
          //   987: ifnull +19 -> 1006
          //   990: aload 5
          //   992: invokevirtual 249	java/io/OutputStream:close	()V
          //   995: goto +11 -> 1006
          //   998: ldc 251
          //   1000: ldc 253
          //   1002: invokestatic 259	android/util/Log:d	(Ljava/lang/String;Ljava/lang/String;)I
          //   1005: pop
          //   1006: aload 8
          //   1008: ifnull +20 -> 1028
          //   1011: aload 8
          //   1013: invokevirtual 260	java/io/InputStream:close	()V
          //   1016: goto +12 -> 1028
          //   1019: ldc 251
          //   1021: ldc_w 262
          //   1024: invokestatic 259	android/util/Log:d	(Ljava/lang/String;Ljava/lang/String;)I
          //   1027: pop
          //   1028: aload 4
          //   1030: ifnull +20 -> 1050
          //   1033: aload 4
          //   1035: invokevirtual 263	java/io/ByteArrayOutputStream:close	()V
          //   1038: goto +12 -> 1050
          //   1041: ldc 251
          //   1043: ldc_w 265
          //   1046: invokestatic 259	android/util/Log:d	(Ljava/lang/String;Ljava/lang/String;)I
          //   1049: pop
          //   1050: aload_3
          //   1051: athrow
          //   1052: iload_2
          //   1053: ifgt +27 -> 1080
          //   1056: getstatic 272	com/baidu/location/e/f:o	I
          //   1059: iconst_1
          //   1060: iadd
          //   1061: putstatic 272	com/baidu/location/e/f:o	I
          //   1064: aload_0
          //   1065: getfield 20	com/baidu/location/e/f$1:c	Lcom/baidu/location/e/f;
          //   1068: astore_3
          //   1069: aload_3
          //   1070: aconst_null
          //   1071: putfield 237	com/baidu/location/e/f:i	Ljava/lang/String;
          //   1074: aload_3
          //   1075: iconst_0
          //   1076: invokevirtual 243	com/baidu/location/e/f:a	(Z)V
          //   1079: return
          //   1080: iconst_0
          //   1081: putstatic 272	com/baidu/location/e/f:o	I
          //   1084: return
          //   1085: astore_3
          //   1086: aload 4
          //   1088: astore_3
          //   1089: goto -270 -> 819
          //   1092: astore_3
          //   1093: aload 4
          //   1095: astore_3
          //   1096: goto -387 -> 709
          //   1099: astore 4
          //   1101: goto -412 -> 689
          //   1104: astore 4
          //   1106: goto -420 -> 686
          //   1109: astore 4
          //   1111: goto -443 -> 668
          //   1114: astore 4
          //   1116: goto -455 -> 661
          //   1119: astore 4
          //   1121: goto -556 -> 565
          //   1124: astore 4
          //   1126: goto -568 -> 558
          //   1129: astore 7
          //   1131: goto -606 -> 525
          //   1134: astore 7
          //   1136: goto -622 -> 514
          //   1139: astore 5
          //   1141: goto -549 -> 592
          //   1144: astore 4
          //   1146: goto -533 -> 613
          //   1149: astore 4
          //   1151: goto -516 -> 635
          //   1154: astore 4
          //   1156: goto -389 -> 767
          //   1159: astore 4
          //   1161: goto -373 -> 788
          //   1164: astore_3
          //   1165: goto -236 -> 929
          //   1168: astore 4
          //   1170: goto -293 -> 877
          //   1173: astore 4
          //   1175: goto -277 -> 898
          //   1178: astore 5
          //   1180: goto -182 -> 998
          //   1183: astore 5
          //   1185: goto -166 -> 1019
          //   1188: astore 4
          //   1190: goto -149 -> 1041
          // Local variable table:
          //   start	length	slot	name	signature
          //   0	1193	0	this	1
          //   428	513	1	i	int
          //   23	1030	2	j	int
          //   4	679	3	localObject1	Object
          //   692	232	3	localObject2	Object
          //   954	97	3	localObject3	Object
          //   1068	7	3	localf	f
          //   1085	1	3	localException1	java.lang.Exception
          //   1088	1	3	localObject4	Object
          //   1092	1	3	localError1	java.lang.Error
          //   1095	1	3	localObject5	Object
          //   1164	1	3	localException2	java.lang.Exception
          //   25	505	4	localObject6	Object
          //   536	13	4	localObject7	Object
          //   553	93	4	localObject8	Object
          //   650	6	4	localObject9	Object
          //   678	416	4	localObject10	Object
          //   1099	1	4	localException3	java.lang.Exception
          //   1104	1	4	localError2	java.lang.Error
          //   1109	1	4	localException4	java.lang.Exception
          //   1114	1	4	localError3	java.lang.Error
          //   1119	1	4	localException5	java.lang.Exception
          //   1124	1	4	localError4	java.lang.Error
          //   1144	1	4	localException6	java.lang.Exception
          //   1149	1	4	localException7	java.lang.Exception
          //   1154	1	4	localException8	java.lang.Exception
          //   1159	1	4	localException9	java.lang.Exception
          //   1168	1	4	localException10	java.lang.Exception
          //   1173	1	4	localException11	java.lang.Exception
          //   1188	1	4	localException12	java.lang.Exception
          //   72	597	5	localObject11	Object
          //   675	6	5	localObject12	Object
          //   694	297	5	localObject13	Object
          //   1139	1	5	localException13	java.lang.Exception
          //   1178	1	5	localException14	java.lang.Exception
          //   1183	1	5	localException15	java.lang.Exception
          //   53	919	6	localObject14	Object
          //   94	887	7	localObject15	Object
          //   1129	1	7	localException16	java.lang.Exception
          //   1134	1	7	localError5	java.lang.Error
          //   320	84	8	localObject16	Object
          //   499	6	8	localObject17	Object
          //   509	503	8	localObject18	Object
          //   312	579	9	localObject19	Object
          //   326	544	10	localObject20	Object
          // Exception table:
          //   from	to	target	type
          //   414	421	499	finally
          //   421	429	499	finally
          //   434	443	499	finally
          //   446	486	499	finally
          //   486	494	499	finally
          //   322	328	536	finally
          //   353	363	536	finally
          //   375	393	536	finally
          //   405	414	536	finally
          //   276	310	650	finally
          //   173	237	675	finally
          //   242	250	675	finally
          //   250	270	675	finally
          //   270	276	675	finally
          //   31	74	692	finally
          //   74	141	692	finally
          //   144	165	692	finally
          //   165	173	692	finally
          //   737	746	954	finally
          //   847	856	954	finally
          //   31	74	1085	java/lang/Exception
          //   74	141	1085	java/lang/Exception
          //   144	165	1085	java/lang/Exception
          //   165	173	1085	java/lang/Exception
          //   31	74	1092	java/lang/Error
          //   74	141	1092	java/lang/Error
          //   144	165	1092	java/lang/Error
          //   165	173	1092	java/lang/Error
          //   173	237	1099	java/lang/Exception
          //   242	250	1099	java/lang/Exception
          //   250	270	1099	java/lang/Exception
          //   270	276	1099	java/lang/Exception
          //   173	237	1104	java/lang/Error
          //   242	250	1104	java/lang/Error
          //   250	270	1104	java/lang/Error
          //   270	276	1104	java/lang/Error
          //   276	310	1109	java/lang/Exception
          //   276	310	1114	java/lang/Error
          //   322	328	1119	java/lang/Exception
          //   353	363	1119	java/lang/Exception
          //   375	393	1119	java/lang/Exception
          //   405	414	1119	java/lang/Exception
          //   322	328	1124	java/lang/Error
          //   353	363	1124	java/lang/Error
          //   375	393	1124	java/lang/Error
          //   405	414	1124	java/lang/Error
          //   414	421	1129	java/lang/Exception
          //   421	429	1129	java/lang/Exception
          //   434	443	1129	java/lang/Exception
          //   446	486	1129	java/lang/Exception
          //   486	494	1129	java/lang/Exception
          //   414	421	1134	java/lang/Error
          //   421	429	1134	java/lang/Error
          //   434	443	1134	java/lang/Error
          //   446	486	1134	java/lang/Error
          //   486	494	1134	java/lang/Error
          //   584	589	1139	java/lang/Exception
          //   605	610	1144	java/lang/Exception
          //   627	632	1149	java/lang/Exception
          //   759	764	1154	java/lang/Exception
          //   780	785	1159	java/lang/Exception
          //   808	813	1164	java/lang/Exception
          //   918	923	1164	java/lang/Exception
          //   869	874	1168	java/lang/Exception
          //   890	895	1173	java/lang/Exception
          //   990	995	1178	java/lang/Exception
          //   1011	1016	1183	java/lang/Exception
          //   1033	1038	1188	java/lang/Exception
        }
      });
      return;
    }
    finally
    {
      label17:
      break label17;
    }
    a(false);
  }
  
  public abstract void a(boolean paramBoolean);
  
  public void b(final String paramString)
  {
    try
    {
      new Thread()
      {
        /* Error */
        public void run()
        {
          // Byte code:
          //   0: aload_0
          //   1: getfield 16	com/baidu/location/e/f$2:b	Lcom/baidu/location/e/f;
          //   4: invokevirtual 29	com/baidu/location/e/f:a	()V
          //   7: aload_0
          //   8: getfield 16	com/baidu/location/e/f$2:b	Lcom/baidu/location/e/f;
          //   11: aload_0
          //   12: getfield 18	com/baidu/location/e/f$2:a	Ljava/lang/String;
          //   15: putfield 32	com/baidu/location/e/f:g	Ljava/lang/String;
          //   18: aconst_null
          //   19: astore 6
          //   21: aconst_null
          //   22: astore_2
          //   23: invokestatic 38	com/baidu/location/e/h:k	()Ljavax/net/ssl/SSLSocketFactory;
          //   26: invokestatic 44	javax/net/ssl/HttpsURLConnection:setDefaultSSLSocketFactory	(Ljavax/net/ssl/SSLSocketFactory;)V
          //   29: new 46	java/lang/StringBuffer
          //   32: dup
          //   33: invokespecial 47	java/lang/StringBuffer:<init>	()V
          //   36: astore_3
          //   37: new 49	java/net/URL
          //   40: dup
          //   41: aload_0
          //   42: getfield 16	com/baidu/location/e/f$2:b	Lcom/baidu/location/e/f;
          //   45: getfield 32	com/baidu/location/e/f:g	Ljava/lang/String;
          //   48: invokespecial 51	java/net/URL:<init>	(Ljava/lang/String;)V
          //   51: astore 4
          //   53: aload 4
          //   55: invokevirtual 55	java/net/URL:openConnection	()Ljava/net/URLConnection;
          //   58: checkcast 40	javax/net/ssl/HttpsURLConnection
          //   61: astore 5
          //   63: aload 5
          //   65: iconst_0
          //   66: invokevirtual 59	javax/net/ssl/HttpsURLConnection:setInstanceFollowRedirects	(Z)V
          //   69: aload 5
          //   71: iconst_1
          //   72: invokevirtual 62	javax/net/ssl/HttpsURLConnection:setDoOutput	(Z)V
          //   75: aload 5
          //   77: iconst_1
          //   78: invokevirtual 65	javax/net/ssl/HttpsURLConnection:setDoInput	(Z)V
          //   81: aload 5
          //   83: getstatic 70	com/baidu/location/e/a:a	I
          //   86: invokevirtual 74	javax/net/ssl/HttpsURLConnection:setConnectTimeout	(I)V
          //   89: aload 5
          //   91: getstatic 76	com/baidu/location/e/a:b	I
          //   94: invokevirtual 79	javax/net/ssl/HttpsURLConnection:setReadTimeout	(I)V
          //   97: aload 5
          //   99: ldc 81
          //   101: invokevirtual 84	javax/net/ssl/HttpsURLConnection:setRequestMethod	(Ljava/lang/String;)V
          //   104: aload 5
          //   106: new 86	com/baidu/location/e/f$a
          //   109: dup
          //   110: aload 4
          //   112: invokespecial 89	com/baidu/location/e/f$a:<init>	(Ljava/net/URL;)V
          //   115: invokevirtual 93	javax/net/ssl/HttpsURLConnection:setHostnameVerifier	(Ljavax/net/ssl/HostnameVerifier;)V
          //   118: aload 5
          //   120: ldc 95
          //   122: ldc 97
          //   124: invokevirtual 101	javax/net/ssl/HttpsURLConnection:setRequestProperty	(Ljava/lang/String;Ljava/lang/String;)V
          //   127: aload 5
          //   129: ldc 103
          //   131: ldc 105
          //   133: invokevirtual 101	javax/net/ssl/HttpsURLConnection:setRequestProperty	(Ljava/lang/String;Ljava/lang/String;)V
          //   136: getstatic 108	com/baidu/location/e/h:aw	Ljava/lang/String;
          //   139: astore 4
          //   141: aload 4
          //   143: ifnull +12 -> 155
          //   146: aload 5
          //   148: ldc 110
          //   150: aload 4
          //   152: invokevirtual 101	javax/net/ssl/HttpsURLConnection:setRequestProperty	(Ljava/lang/String;Ljava/lang/String;)V
          //   155: aload_0
          //   156: getfield 16	com/baidu/location/e/f$2:b	Lcom/baidu/location/e/f;
          //   159: getfield 114	com/baidu/location/e/f:j	Ljava/util/Map;
          //   162: invokeinterface 120 1 0
          //   167: invokeinterface 126 1 0
          //   172: astore 4
          //   174: aload 4
          //   176: invokeinterface 132 1 0
          //   181: ifeq +59 -> 240
          //   184: aload 4
          //   186: invokeinterface 136 1 0
          //   191: checkcast 138	java/util/Map$Entry
          //   194: astore 6
          //   196: aload_3
          //   197: aload 6
          //   199: invokeinterface 141 1 0
          //   204: checkcast 143	java/lang/String
          //   207: invokevirtual 147	java/lang/StringBuffer:append	(Ljava/lang/String;)Ljava/lang/StringBuffer;
          //   210: pop
          //   211: aload_3
          //   212: ldc 149
          //   214: invokevirtual 147	java/lang/StringBuffer:append	(Ljava/lang/String;)Ljava/lang/StringBuffer;
          //   217: pop
          //   218: aload_3
          //   219: aload 6
          //   221: invokeinterface 152 1 0
          //   226: invokevirtual 155	java/lang/StringBuffer:append	(Ljava/lang/Object;)Ljava/lang/StringBuffer;
          //   229: pop
          //   230: aload_3
          //   231: ldc 157
          //   233: invokevirtual 147	java/lang/StringBuffer:append	(Ljava/lang/String;)Ljava/lang/StringBuffer;
          //   236: pop
          //   237: goto -63 -> 174
          //   240: aload_3
          //   241: invokevirtual 161	java/lang/StringBuffer:length	()I
          //   244: ifle +14 -> 258
          //   247: aload_3
          //   248: aload_3
          //   249: invokevirtual 161	java/lang/StringBuffer:length	()I
          //   252: iconst_1
          //   253: isub
          //   254: invokevirtual 165	java/lang/StringBuffer:deleteCharAt	(I)Ljava/lang/StringBuffer;
          //   257: pop
          //   258: aload 5
          //   260: invokevirtual 169	javax/net/ssl/HttpsURLConnection:getOutputStream	()Ljava/io/OutputStream;
          //   263: astore 6
          //   265: aload 6
          //   267: aload_3
          //   268: invokevirtual 173	java/lang/StringBuffer:toString	()Ljava/lang/String;
          //   271: invokevirtual 177	java/lang/String:getBytes	()[B
          //   274: invokevirtual 183	java/io/OutputStream:write	([B)V
          //   277: aload 6
          //   279: invokevirtual 186	java/io/OutputStream:flush	()V
          //   282: aload 5
          //   284: invokevirtual 189	javax/net/ssl/HttpsURLConnection:getResponseCode	()I
          //   287: sipush 200
          //   290: if_icmpne +285 -> 575
          //   293: aload 5
          //   295: invokevirtual 193	javax/net/ssl/HttpsURLConnection:getInputStream	()Ljava/io/InputStream;
          //   298: astore_3
          //   299: aload_3
          //   300: astore 4
          //   302: aload_3
          //   303: astore 7
          //   305: aload_3
          //   306: astore 9
          //   308: aload 5
          //   310: invokevirtual 196	javax/net/ssl/HttpsURLConnection:getContentEncoding	()Ljava/lang/String;
          //   313: astore 8
          //   315: aload_3
          //   316: astore_2
          //   317: aload 8
          //   319: ifnull +49 -> 368
          //   322: aload_3
          //   323: astore_2
          //   324: aload_3
          //   325: astore 4
          //   327: aload_3
          //   328: astore 7
          //   330: aload_3
          //   331: astore 9
          //   333: aload 8
          //   335: ldc 105
          //   337: invokevirtual 200	java/lang/String:contains	(Ljava/lang/CharSequence;)Z
          //   340: ifeq +28 -> 368
          //   343: aload_3
          //   344: astore 4
          //   346: aload_3
          //   347: astore 7
          //   349: aload_3
          //   350: astore 9
          //   352: new 202	java/util/zip/GZIPInputStream
          //   355: dup
          //   356: new 204	java/io/BufferedInputStream
          //   359: dup
          //   360: aload_3
          //   361: invokespecial 207	java/io/BufferedInputStream:<init>	(Ljava/io/InputStream;)V
          //   364: invokespecial 208	java/util/zip/GZIPInputStream:<init>	(Ljava/io/InputStream;)V
          //   367: astore_2
          //   368: aload_2
          //   369: astore 4
          //   371: aload_2
          //   372: astore 7
          //   374: aload_2
          //   375: astore 9
          //   377: new 210	java/io/ByteArrayOutputStream
          //   380: dup
          //   381: invokespecial 211	java/io/ByteArrayOutputStream:<init>	()V
          //   384: astore 8
          //   386: aload_2
          //   387: astore 7
          //   389: aload 6
          //   391: astore 9
          //   393: aload 5
          //   395: astore 10
          //   397: aload 8
          //   399: astore 11
          //   401: sipush 1024
          //   404: newarray byte
          //   406: astore_3
          //   407: aload_2
          //   408: astore 7
          //   410: aload 6
          //   412: astore 9
          //   414: aload 5
          //   416: astore 10
          //   418: aload 8
          //   420: astore 11
          //   422: aload_2
          //   423: aload_3
          //   424: invokevirtual 217	java/io/InputStream:read	([B)I
          //   427: istore_1
          //   428: iload_1
          //   429: iconst_m1
          //   430: if_icmpeq +29 -> 459
          //   433: aload_2
          //   434: astore 7
          //   436: aload 6
          //   438: astore 9
          //   440: aload 5
          //   442: astore 10
          //   444: aload 8
          //   446: astore 11
          //   448: aload 8
          //   450: aload_3
          //   451: iconst_0
          //   452: iload_1
          //   453: invokevirtual 220	java/io/ByteArrayOutputStream:write	([BII)V
          //   456: goto -49 -> 407
          //   459: aload_2
          //   460: astore 7
          //   462: aload 6
          //   464: astore 9
          //   466: aload 5
          //   468: astore 10
          //   470: aload 8
          //   472: astore 11
          //   474: aload_0
          //   475: getfield 16	com/baidu/location/e/f$2:b	Lcom/baidu/location/e/f;
          //   478: new 143	java/lang/String
          //   481: dup
          //   482: aload 8
          //   484: invokevirtual 223	java/io/ByteArrayOutputStream:toByteArray	()[B
          //   487: ldc 225
          //   489: invokespecial 228	java/lang/String:<init>	([BLjava/lang/String;)V
          //   492: putfield 231	com/baidu/location/e/f:i	Ljava/lang/String;
          //   495: aload_2
          //   496: astore 7
          //   498: aload 6
          //   500: astore 9
          //   502: aload 5
          //   504: astore 10
          //   506: aload 8
          //   508: astore 11
          //   510: aload_0
          //   511: getfield 16	com/baidu/location/e/f$2:b	Lcom/baidu/location/e/f;
          //   514: iconst_1
          //   515: invokevirtual 233	com/baidu/location/e/f:a	(Z)V
          //   518: goto +75 -> 593
          //   521: astore 4
          //   523: aload_2
          //   524: astore_3
          //   525: aload 8
          //   527: astore_2
          //   528: goto +212 -> 740
          //   531: astore 4
          //   533: aload_2
          //   534: astore_3
          //   535: aload 8
          //   537: astore_2
          //   538: goto +377 -> 915
          //   541: astore_2
          //   542: aconst_null
          //   543: astore 7
          //   545: aload 4
          //   547: astore_3
          //   548: aload 7
          //   550: astore 4
          //   552: goto +548 -> 1100
          //   555: astore 4
          //   557: aconst_null
          //   558: astore_2
          //   559: aload 7
          //   561: astore_3
          //   562: goto +178 -> 740
          //   565: astore 4
          //   567: aconst_null
          //   568: astore_2
          //   569: aload 9
          //   571: astore_3
          //   572: goto +343 -> 915
          //   575: aload_0
          //   576: getfield 16	com/baidu/location/e/f$2:b	Lcom/baidu/location/e/f;
          //   579: astore_3
          //   580: aload_3
          //   581: aconst_null
          //   582: putfield 231	com/baidu/location/e/f:i	Ljava/lang/String;
          //   585: aload_3
          //   586: iconst_0
          //   587: invokevirtual 233	com/baidu/location/e/f:a	(Z)V
          //   590: aconst_null
          //   591: astore 8
          //   593: aload 5
          //   595: invokevirtual 236	javax/net/ssl/HttpsURLConnection:disconnect	()V
          //   598: aload 6
          //   600: invokevirtual 239	java/io/OutputStream:close	()V
          //   603: goto +11 -> 614
          //   606: ldc 241
          //   608: ldc 243
          //   610: invokestatic 249	android/util/Log:d	(Ljava/lang/String;Ljava/lang/String;)I
          //   613: pop
          //   614: aload_2
          //   615: ifnull +18 -> 633
          //   618: aload_2
          //   619: invokevirtual 250	java/io/InputStream:close	()V
          //   622: goto +11 -> 633
          //   625: ldc 241
          //   627: ldc 252
          //   629: invokestatic 249	android/util/Log:d	(Ljava/lang/String;Ljava/lang/String;)I
          //   632: pop
          //   633: aload 8
          //   635: ifnull +448 -> 1083
          //   638: aload 8
          //   640: astore_2
          //   641: goto +430 -> 1071
          //   644: astore_2
          //   645: aconst_null
          //   646: astore_3
          //   647: aload_3
          //   648: astore 4
          //   650: goto +450 -> 1100
          //   653: astore 4
          //   655: aconst_null
          //   656: astore_3
          //   657: aload_3
          //   658: astore_2
          //   659: goto +81 -> 740
          //   662: astore 4
          //   664: aconst_null
          //   665: astore_3
          //   666: aload_3
          //   667: astore_2
          //   668: goto +247 -> 915
          //   671: astore_2
          //   672: aconst_null
          //   673: astore_3
          //   674: aload_3
          //   675: astore 6
          //   677: aload 6
          //   679: astore 4
          //   681: goto +419 -> 1100
          //   684: astore 4
          //   686: aconst_null
          //   687: astore_3
          //   688: aload_3
          //   689: astore 6
          //   691: aload 6
          //   693: astore_2
          //   694: goto +46 -> 740
          //   697: astore 4
          //   699: aconst_null
          //   700: astore_3
          //   701: aload_3
          //   702: astore 6
          //   704: aload 6
          //   706: astore_2
          //   707: goto +208 -> 915
          //   710: astore_3
          //   711: aconst_null
          //   712: astore 5
          //   714: aload 5
          //   716: astore_2
          //   717: aload_2
          //   718: astore 4
          //   720: aload_2
          //   721: astore 7
          //   723: goto +394 -> 1117
          //   726: astore 4
          //   728: aconst_null
          //   729: astore_3
          //   730: aload_3
          //   731: astore 6
          //   733: aload 6
          //   735: astore 5
          //   737: aload 5
          //   739: astore_2
          //   740: aload_3
          //   741: astore 7
          //   743: aload 6
          //   745: astore 9
          //   747: aload 5
          //   749: astore 10
          //   751: aload_2
          //   752: astore 11
          //   754: aload 4
          //   756: invokevirtual 255	java/lang/Error:printStackTrace	()V
          //   759: aload_3
          //   760: astore 7
          //   762: aload 6
          //   764: astore 9
          //   766: aload 5
          //   768: astore 10
          //   770: aload_2
          //   771: astore 11
          //   773: ldc 241
          //   775: ldc_w 257
          //   778: invokestatic 259	android/util/Log:i	(Ljava/lang/String;Ljava/lang/String;)I
          //   781: pop
          //   782: aload_3
          //   783: astore 7
          //   785: aload 6
          //   787: astore 9
          //   789: aload 5
          //   791: astore 10
          //   793: aload_2
          //   794: astore 11
          //   796: aload_0
          //   797: getfield 16	com/baidu/location/e/f$2:b	Lcom/baidu/location/e/f;
          //   800: astore 4
          //   802: aload_3
          //   803: astore 7
          //   805: aload 6
          //   807: astore 9
          //   809: aload 5
          //   811: astore 10
          //   813: aload_2
          //   814: astore 11
          //   816: aload 4
          //   818: aconst_null
          //   819: putfield 231	com/baidu/location/e/f:i	Ljava/lang/String;
          //   822: aload_3
          //   823: astore 7
          //   825: aload 6
          //   827: astore 9
          //   829: aload 5
          //   831: astore 10
          //   833: aload_2
          //   834: astore 11
          //   836: aload 4
          //   838: iconst_0
          //   839: invokevirtual 233	com/baidu/location/e/f:a	(Z)V
          //   842: aload 5
          //   844: ifnull +8 -> 852
          //   847: aload 5
          //   849: invokevirtual 236	javax/net/ssl/HttpsURLConnection:disconnect	()V
          //   852: aload 6
          //   854: ifnull +19 -> 873
          //   857: aload 6
          //   859: invokevirtual 239	java/io/OutputStream:close	()V
          //   862: goto +11 -> 873
          //   865: ldc 241
          //   867: ldc 243
          //   869: invokestatic 249	android/util/Log:d	(Ljava/lang/String;Ljava/lang/String;)I
          //   872: pop
          //   873: aload_3
          //   874: ifnull +18 -> 892
          //   877: aload_3
          //   878: invokevirtual 250	java/io/InputStream:close	()V
          //   881: goto +11 -> 892
          //   884: ldc 241
          //   886: ldc 252
          //   888: invokestatic 249	android/util/Log:d	(Ljava/lang/String;Ljava/lang/String;)I
          //   891: pop
          //   892: aload_2
          //   893: ifnull +190 -> 1083
          //   896: aload_2
          //   897: invokevirtual 260	java/io/ByteArrayOutputStream:close	()V
          //   900: return
          //   901: astore 4
          //   903: aconst_null
          //   904: astore_3
          //   905: aload_3
          //   906: astore 6
          //   908: aload 6
          //   910: astore 5
          //   912: aload 5
          //   914: astore_2
          //   915: aload_3
          //   916: astore 7
          //   918: aload 6
          //   920: astore 9
          //   922: aload 5
          //   924: astore 10
          //   926: aload_2
          //   927: astore 11
          //   929: aload 4
          //   931: invokevirtual 261	java/lang/Exception:printStackTrace	()V
          //   934: aload_3
          //   935: astore 7
          //   937: aload 6
          //   939: astore 9
          //   941: aload 5
          //   943: astore 10
          //   945: aload_2
          //   946: astore 11
          //   948: ldc 241
          //   950: ldc_w 263
          //   953: invokestatic 259	android/util/Log:i	(Ljava/lang/String;Ljava/lang/String;)I
          //   956: pop
          //   957: aload_3
          //   958: astore 7
          //   960: aload 6
          //   962: astore 9
          //   964: aload 5
          //   966: astore 10
          //   968: aload_2
          //   969: astore 11
          //   971: aload_0
          //   972: getfield 16	com/baidu/location/e/f$2:b	Lcom/baidu/location/e/f;
          //   975: astore 4
          //   977: aload_3
          //   978: astore 7
          //   980: aload 6
          //   982: astore 9
          //   984: aload 5
          //   986: astore 10
          //   988: aload_2
          //   989: astore 11
          //   991: aload 4
          //   993: aconst_null
          //   994: putfield 231	com/baidu/location/e/f:i	Ljava/lang/String;
          //   997: aload_3
          //   998: astore 7
          //   1000: aload 6
          //   1002: astore 9
          //   1004: aload 5
          //   1006: astore 10
          //   1008: aload_2
          //   1009: astore 11
          //   1011: aload 4
          //   1013: iconst_0
          //   1014: invokevirtual 233	com/baidu/location/e/f:a	(Z)V
          //   1017: aload 5
          //   1019: ifnull +8 -> 1027
          //   1022: aload 5
          //   1024: invokevirtual 236	javax/net/ssl/HttpsURLConnection:disconnect	()V
          //   1027: aload 6
          //   1029: ifnull +19 -> 1048
          //   1032: aload 6
          //   1034: invokevirtual 239	java/io/OutputStream:close	()V
          //   1037: goto +11 -> 1048
          //   1040: ldc 241
          //   1042: ldc 243
          //   1044: invokestatic 249	android/util/Log:d	(Ljava/lang/String;Ljava/lang/String;)I
          //   1047: pop
          //   1048: aload_3
          //   1049: ifnull +18 -> 1067
          //   1052: aload_3
          //   1053: invokevirtual 250	java/io/InputStream:close	()V
          //   1056: goto +11 -> 1067
          //   1059: ldc 241
          //   1061: ldc 252
          //   1063: invokestatic 249	android/util/Log:d	(Ljava/lang/String;Ljava/lang/String;)I
          //   1066: pop
          //   1067: aload_2
          //   1068: ifnull +15 -> 1083
          //   1071: goto -175 -> 896
          //   1074: ldc 241
          //   1076: ldc_w 265
          //   1079: invokestatic 249	android/util/Log:d	(Ljava/lang/String;Ljava/lang/String;)I
          //   1082: pop
          //   1083: return
          //   1084: astore_2
          //   1085: aload 11
          //   1087: astore 4
          //   1089: aload 10
          //   1091: astore 5
          //   1093: aload 9
          //   1095: astore 6
          //   1097: aload 7
          //   1099: astore_3
          //   1100: aload 5
          //   1102: astore 8
          //   1104: aload 6
          //   1106: astore 7
          //   1108: aload_3
          //   1109: astore 5
          //   1111: aload 8
          //   1113: astore 6
          //   1115: aload_2
          //   1116: astore_3
          //   1117: aload 6
          //   1119: ifnull +8 -> 1127
          //   1122: aload 6
          //   1124: invokevirtual 236	javax/net/ssl/HttpsURLConnection:disconnect	()V
          //   1127: aload 7
          //   1129: ifnull +19 -> 1148
          //   1132: aload 7
          //   1134: invokevirtual 239	java/io/OutputStream:close	()V
          //   1137: goto +11 -> 1148
          //   1140: ldc 241
          //   1142: ldc 243
          //   1144: invokestatic 249	android/util/Log:d	(Ljava/lang/String;Ljava/lang/String;)I
          //   1147: pop
          //   1148: aload 5
          //   1150: ifnull +19 -> 1169
          //   1153: aload 5
          //   1155: invokevirtual 250	java/io/InputStream:close	()V
          //   1158: goto +11 -> 1169
          //   1161: ldc 241
          //   1163: ldc 252
          //   1165: invokestatic 249	android/util/Log:d	(Ljava/lang/String;Ljava/lang/String;)I
          //   1168: pop
          //   1169: aload 4
          //   1171: ifnull +20 -> 1191
          //   1174: aload 4
          //   1176: invokevirtual 260	java/io/ByteArrayOutputStream:close	()V
          //   1179: goto +12 -> 1191
          //   1182: ldc 241
          //   1184: ldc_w 265
          //   1187: invokestatic 249	android/util/Log:d	(Ljava/lang/String;Ljava/lang/String;)I
          //   1190: pop
          //   1191: aload_3
          //   1192: athrow
          //   1193: astore_3
          //   1194: goto -588 -> 606
          //   1197: astore_2
          //   1198: goto -573 -> 625
          //   1201: astore 4
          //   1203: goto -338 -> 865
          //   1206: astore_3
          //   1207: goto -323 -> 884
          //   1210: astore_2
          //   1211: goto -137 -> 1074
          //   1214: astore 4
          //   1216: goto -176 -> 1040
          //   1219: astore_3
          //   1220: goto -161 -> 1059
          //   1223: astore_2
          //   1224: goto -84 -> 1140
          //   1227: astore_2
          //   1228: goto -67 -> 1161
          //   1231: astore_2
          //   1232: goto -50 -> 1182
          // Local variable table:
          //   start	length	slot	name	signature
          //   0	1235	0	this	2
          //   427	26	1	i	int
          //   22	516	2	localObject1	Object
          //   541	1	2	localObject2	Object
          //   558	83	2	localObject3	Object
          //   644	1	2	localObject4	Object
          //   658	10	2	localObject5	Object
          //   671	1	2	localObject6	Object
          //   693	375	2	localObject7	Object
          //   1084	32	2	localObject8	Object
          //   1197	1	2	localException1	java.lang.Exception
          //   1210	1	2	localException2	java.lang.Exception
          //   1223	1	2	localException3	java.lang.Exception
          //   1227	1	2	localException4	java.lang.Exception
          //   1231	1	2	localException5	java.lang.Exception
          //   36	666	3	localObject9	Object
          //   710	1	3	localObject10	Object
          //   729	463	3	localObject11	Object
          //   1193	1	3	localException6	java.lang.Exception
          //   1206	1	3	localException7	java.lang.Exception
          //   1219	1	3	localException8	java.lang.Exception
          //   51	319	4	localObject12	Object
          //   521	1	4	localError1	java.lang.Error
          //   531	15	4	localException9	java.lang.Exception
          //   550	1	4	localObject13	Object
          //   555	1	4	localError2	java.lang.Error
          //   565	1	4	localException10	java.lang.Exception
          //   648	1	4	localObject14	Object
          //   653	1	4	localError3	java.lang.Error
          //   662	1	4	localException11	java.lang.Exception
          //   679	1	4	localObject15	Object
          //   684	1	4	localError4	java.lang.Error
          //   697	1	4	localException12	java.lang.Exception
          //   718	1	4	localObject16	Object
          //   726	29	4	localError5	java.lang.Error
          //   800	37	4	localf	f
          //   901	29	4	localException13	java.lang.Exception
          //   975	200	4	localObject17	Object
          //   1201	1	4	localException14	java.lang.Exception
          //   1214	1	4	localException15	java.lang.Exception
          //   61	1093	5	localObject18	Object
          //   19	1104	6	localObject19	Object
          //   303	830	7	localObject20	Object
          //   313	799	8	localObject21	Object
          //   306	788	9	localObject22	Object
          //   395	695	10	localObject23	Object
          //   399	687	11	localObject24	Object
          // Exception table:
          //   from	to	target	type
          //   401	407	521	java/lang/Error
          //   422	428	521	java/lang/Error
          //   448	456	521	java/lang/Error
          //   474	495	521	java/lang/Error
          //   510	518	521	java/lang/Error
          //   401	407	531	java/lang/Exception
          //   422	428	531	java/lang/Exception
          //   448	456	531	java/lang/Exception
          //   474	495	531	java/lang/Exception
          //   510	518	531	java/lang/Exception
          //   308	315	541	finally
          //   333	343	541	finally
          //   352	368	541	finally
          //   377	386	541	finally
          //   308	315	555	java/lang/Error
          //   333	343	555	java/lang/Error
          //   352	368	555	java/lang/Error
          //   377	386	555	java/lang/Error
          //   308	315	565	java/lang/Exception
          //   333	343	565	java/lang/Exception
          //   352	368	565	java/lang/Exception
          //   377	386	565	java/lang/Exception
          //   265	299	644	finally
          //   575	590	644	finally
          //   265	299	653	java/lang/Error
          //   575	590	653	java/lang/Error
          //   265	299	662	java/lang/Exception
          //   575	590	662	java/lang/Exception
          //   63	141	671	finally
          //   146	155	671	finally
          //   155	174	671	finally
          //   174	237	671	finally
          //   240	258	671	finally
          //   258	265	671	finally
          //   63	141	684	java/lang/Error
          //   146	155	684	java/lang/Error
          //   155	174	684	java/lang/Error
          //   174	237	684	java/lang/Error
          //   240	258	684	java/lang/Error
          //   258	265	684	java/lang/Error
          //   63	141	697	java/lang/Exception
          //   146	155	697	java/lang/Exception
          //   155	174	697	java/lang/Exception
          //   174	237	697	java/lang/Exception
          //   240	258	697	java/lang/Exception
          //   258	265	697	java/lang/Exception
          //   23	63	710	finally
          //   23	63	726	java/lang/Error
          //   23	63	901	java/lang/Exception
          //   401	407	1084	finally
          //   422	428	1084	finally
          //   448	456	1084	finally
          //   474	495	1084	finally
          //   510	518	1084	finally
          //   754	759	1084	finally
          //   773	782	1084	finally
          //   796	802	1084	finally
          //   816	822	1084	finally
          //   836	842	1084	finally
          //   929	934	1084	finally
          //   948	957	1084	finally
          //   971	977	1084	finally
          //   991	997	1084	finally
          //   1011	1017	1084	finally
          //   598	603	1193	java/lang/Exception
          //   618	622	1197	java/lang/Exception
          //   857	862	1201	java/lang/Exception
          //   877	881	1206	java/lang/Exception
          //   896	900	1210	java/lang/Exception
          //   1032	1037	1214	java/lang/Exception
          //   1052	1056	1219	java/lang/Exception
          //   1132	1137	1223	java/lang/Exception
          //   1153	1158	1227	java/lang/Exception
          //   1174	1179	1231	java/lang/Exception
        }
      }.start();
      return;
    }
    finally
    {
      label13:
      break label13;
    }
    a(false);
  }
  
  private static class a
    implements HostnameVerifier
  {
    private URL a;
    
    public a(URL paramURL)
    {
      this.a = paramURL;
    }
    
    public boolean verify(String paramString, SSLSession paramSSLSession)
    {
      return this.a.getHost().equals(paramString);
    }
  }
}


/* Location:           E:\android_tools\AndroidKiller_v1.3.1\projects\hoxin-release\ProjectSrc\smali\
 * Qualified Name:     com.baidu.location.e.f
 * JD-Core Version:    0.7.0.1
 */